Workbook
Name AUpdate: 1
Name BUpdate: 1
Name GUpdate: 0
Name TUpdate: 1

Sheet Revenue
A1: 個股 | B1: 名稱 | C1: 產業別 | D1: =營收表現!C$3 -> 202508單月合併營收月變動(%) | E1: =營收表現!D$3 -> 202509單月合併營收月變動(%) | F1: =營收表現!E$3 -> 202510單月合併營收月變動(%) | G1: =營收表現!F$3 -> 202511單月合併營收月變動(%) | H1: =營收表現!G$3 -> 202512單月合併營收月變動(%) | I1: =營收表現!H$3 -> 202601單月合併營收月變動(%) | J1: =營收表現!I$3 -> 202508單月合併營收年成長(%) | K1: =營收表現!J$3 -> 202509單月合併營收年成長(%) | ... O1: =營收表現!N$3 -> 202601單月合併營收年成長(%)
A2: 2330 | B2: =IFERROR(INDEX(營收表現!B$6:B$3000,MATCH($A2,營收表現!$A$6:$A$3000,0)),"") -> 台積電 | C2: =IFERROR(INDEX(類別!G$4:G$3000,MATCH($A2,類別!$C$4:$C$3000,0)),"") -> IC代工 | D2: =IFERROR(IF(INDEX(營收表現!C$6:C$3000,MATCH($A2,營收表現!$A$6:$A$3000,0))="","",INDEX(營收表現!C$6:C$3000,MATCH($A2,營收表現!$A$6:$A$3000,0))),"") -> 3.9 | E2: =IFERROR(IF(INDEX(營收表現!D$6:D$3000,MATCH($A2,營收表現!$A$6:$A$3000,0))="","",INDEX(營收表現!D$6:D$3000,MATCH($A2,營收表現!$A$6:$A$3000,0))),"") -> -1.43 | F2: =IFERROR(IF(INDEX(營收表現!E$6:E$3000,MATCH($A2,營收表現!$A$6:$A$3000,0))="","",INDEX(營收表現!E$6:E$3000,MATCH($A2,營收表現!$A$6:$A$3000,0))),"") -> 11.03 | G2: =IFERROR(IF(INDEX(營收表現!F$6:F$3000,MATCH($A2,營收表現!$A$6:$A$3000,0))="","",INDEX(營收表現!F$6:F$3000,MATCH($A2,營收表現!$A$6:$A$3000,0))),"") -> -6.49 | H2: =IFERROR(IF(INDEX(營收表現!G$6:G$3000,MATCH($A2,營收表現!$A$6:$A$3000,0))="","",INDEX(營收表現!G$6:G$3000,MATCH($A2,營收表現!$A$6:$A$3000,0))),"") -> -2.51 | I2: =IFERROR(IF(INDEX(營收表現!H$6:H$3000,MATCH($A2,營收表現!$A$6:$A$3000,0))="","",INDEX(營收表現!H$6:H$3000,MATCH($A2,營收表現!$A$6:$A$3000,0))),"") -> 19.78 | J2: =IFERROR(IF(INDEX(營收表現!I$6:I$3000,MATCH($A2,營收表現!$A$6:$A$3000,0))="","",INDEX(營收表現!I$6:I$3000,MATCH($A2,營收表現!$A$6:$A$3000,0))),"") -> 33.84 | K2: =IFERROR(IF(INDEX(營收表現!J$6:J$3000,MATCH($A2,營收表現!$A$6:$A$3000,0))="","",INDEX(營收表現!J$6:J$3000,MATCH($A2,營收表現!$A$6:$A$3000,0))),"") -> 31.41 | ... N2: =IFERROR(IF(INDEX(營收表現!M$6:M$3000,MATCH($A2,營收表現!$A$6:$A$3000,0))="","",INDEX(營收表現!M$6:M$3000,MATCH($A2,營收表現!$A$6:$A$3000,0))),"") -> 20.43 | O2: =IF(INDEX(營收表現!N$6:N$3000,MATCH($A2,營收表現!$A$6:$A$3000,0))="","",INDEX(營收表現!N$6:N$3000,MATCH($A2,營收表現!$A$6:$A$3000,0))) -> 36.81
A3: 2454 | B3: =IFERROR(INDEX(營收表現!B$6:B$3000,MATCH($A3,營收表現!$A$6:$A$3000,0)),"") -> 聯發科 | C3: =IFERROR(INDEX(類別!G$4:G$3000,MATCH($A3,類別!$C$4:$C$3000,0)),"") -> 網通IC | D3: =IFERROR(IF(INDEX(營收表現!C$6:C$3000,MATCH($A3,營收表現!$A$6:$A$3000,0))="","",INDEX(營收表現!C$6:C$3000,MATCH($A3,營收表現!$A$6:$A$3000,0))),"") -> 3.07 | E3: =IFERROR(IF(INDEX(營收表現!D$6:D$3000,MATCH($A3,營收表現!$A$6:$A$3000,0))="","",INDEX(營收表現!D$6:D$3000,MATCH($A3,營收表現!$A$6:$A$3000,0))),"") -> 21.96 | F3: =IFERROR(IF(INDEX(營收表現!E$6:E$3000,MATCH($A3,營收表現!$A$6:$A$3000,0))="","",INDEX(營收表現!E$6:E$3000,MATCH($A3,營收表現!$A$6:$A$3000,0))),"") -> -4.24 | G3: =IFERROR(IF(INDEX(營收表現!F$6:F$3000,MATCH($A3,營收表現!$A$6:$A$3000,0))="","",INDEX(營收表現!F$6:F$3000,MATCH($A3,營收表現!$A$6:$A$3000,0))),"") -> -9.86 | H3: =IFERROR(IF(INDEX(營收表現!G$6:G$3000,MATCH($A3,營收表現!$A$6:$A$3000,0))="","",INDEX(營收表現!G$6:G$3000,MATCH($A3,營收表現!$A$6:$A$3000,0))),"") -> 9.32 | I3: =IFERROR(IF(INDEX(營收表現!H$6:H$3000,MATCH($A3,營收表現!$A$6:$A$3000,0))="","",INDEX(營收表現!H$6:H$3000,MATCH($A3,營收表現!$A$6:$A$3000,0))),"") | J3: =IFERROR(IF(INDEX(營收表現!I$6:I$3000,MATCH($A3,營收表現!$A$6:$A$3000,0))="","",INDEX(營收表現!I$6:I$3000,MATCH($A3,營收表現!$A$6:$A$3000,0))),"") -> 7.27 | K3: =IFERROR(IF(INDEX(營收表現!J$6:J$3000,MATCH($A3,營收表現!$A$6:$A$3000,0))="","",INDEX(營收表現!J$6:J$3000,MATCH($A3,營收表現!$A$6:$A$3000,0))),"") -> 21.61 | ... N3: =IFERROR(IF(INDEX(營收表現!M$6:M$3000,MATCH($A3,營收表現!$A$6:$A$3000,0))="","",INDEX(營收表現!M$6:M$3000,MATCH($A3,營收表現!$A$6:$A$3000,0))),"") -> 22.99 | O3: =IF(INDEX(營收表現!N$6:N$3000,MATCH($A3,營收表現!$A$6:$A$3000,0))="","",INDEX(營收表現!N$6:N$3000,MATCH($A3,營收表現!$A$6:$A$3000,0)))
A4: 2338 | B4: =IFERROR(INDEX(營收表現!B$6:B$3000,MATCH($A4,營收表現!$A$6:$A$3000,0)),"") -> 光罩 | C4: =IFERROR(INDEX(類別!G$4:G$3000,MATCH($A4,類別!$C$4:$C$3000,0)),"") -> 半導體設備 | D4: =IFERROR(IF(INDEX(營收表現!C$6:C$3000,MATCH($A4,營收表現!$A$6:$A$3000,0))="","",INDEX(營收表現!C$6:C$3000,MATCH($A4,營收表現!$A$6:$A$3000,0))),"") -> 12.2 | E4: =IFERROR(IF(INDEX(營收表現!D$6:D$3000,MATCH($A4,營收表現!$A$6:$A$3000,0))="","",INDEX(營收表現!D$6:D$3000,MATCH($A4,營收表現!$A$6:$A$3000,0))),"") -> -22.02 | F4: =IFERROR(IF(INDEX(營收表現!E$6:E$3000,MATCH($A4,營收表現!$A$6:$A$3000,0))="","",INDEX(營收表現!E$6:E$3000,MATCH($A4,營收表現!$A$6:$A$3000,0))),"") -> 2.37 | G4: =IFERROR(IF(INDEX(營收表現!F$6:F$3000,MATCH($A4,營收表現!$A$6:$A$3000,0))="","",INDEX(營收表現!F$6:F$3000,MATCH($A4,營收表現!$A$6:$A$3000,0))),"") -> 5.87 | H4: =IFERROR(IF(INDEX(營收表現!G$6:G$3000,MATCH($A4,營收表現!$A$6:$A$3000,0))="","",INDEX(營收表現!G$6:G$3000,MATCH($A4,營收表現!$A$6:$A$3000,0))),"") -> 4.05 | I4: =IFERROR(IF(INDEX(營收表現!H$6:H$3000,MATCH($A4,營收表現!$A$6:$A$3000,0))="","",INDEX(營收表現!H$6:H$3000,MATCH($A4,營收表現!$A$6:$A$3000,0))),"") -> 12.4 | J4: =IFERROR(IF(INDEX(營收表現!I$6:I$3000,MATCH($A4,營收表現!$A$6:$A$3000,0))="","",INDEX(營收表現!I$6:I$3000,MATCH($A4,營收表現!$A$6:$A$3000,0))),"") -> -2.64 | K4: =IFERROR(IF(INDEX(營收表現!J$6:J$3000,MATCH($A4,營收表現!$A$6:$A$3000,0))="","",INDEX(營收表現!J$6:J$3000,MATCH($A4,營收表現!$A$6:$A$3000,0))),"") -> -33.69 | ... N4: =IFERROR(IF(INDEX(營收表現!M$6:M$3000,MATCH($A4,營收表現!$A$6:$A$3000,0))="","",INDEX(營收表現!M$6:M$3000,MATCH($A4,營收表現!$A$6:$A$3000,0))),"") -> -26.79 | O4: =IF(INDEX(營收表現!N$6:N$3000,MATCH($A4,營收表現!$A$6:$A$3000,0))="","",INDEX(營收表現!N$6:N$3000,MATCH($A4,營收表現!$A$6:$A$3000,0))) -> -1.57
A5: 2449 | B5: =IFERROR(INDEX(營收表現!B$6:B$3000,MATCH($A5,營收表現!$A$6:$A$3000,0)),"") -> 京元電子 | C5: =IFERROR(INDEX(類別!G$4:G$3000,MATCH($A5,類別!$C$4:$C$3000,0)),"") -> IC封測 | D5: =IFERROR(IF(INDEX(營收表現!C$6:C$3000,MATCH($A5,營收表現!$A$6:$A$3000,0))="","",INDEX(營收表現!C$6:C$3000,MATCH($A5,營收表現!$A$6:$A$3000,0))),"") -> 6.26 | E5: =IFERROR(IF(INDEX(營收表現!D$6:D$3000,MATCH($A5,營收表現!$A$6:$A$3000,0))="","",INDEX(營收表現!D$6:D$3000,MATCH($A5,營收表現!$A$6:$A$3000,0))),"") -> 5.5 | F5: =IFERROR(IF(INDEX(營收表現!E$6:E$3000,MATCH($A5,營收表現!$A$6:$A$3000,0))="","",INDEX(營收表現!E$6:E$3000,MATCH($A5,營收表現!$A$6:$A$3000,0))),"") -> 4.51 | G5: =IFERROR(IF(INDEX(營收表現!F$6:F$3000,MATCH($A5,營收表現!$A$6:$A$3000,0))="","",INDEX(營收表現!F$6:F$3000,MATCH($A5,營收表現!$A$6:$A$3000,0))),"") -> -3.69 | H5: =IFERROR(IF(INDEX(營收表現!G$6:G$3000,MATCH($A5,營收表現!$A$6:$A$3000,0))="","",INDEX(營收表現!G$6:G$3000,MATCH($A5,營收表現!$A$6:$A$3000,0))),"") -> -1.16 | I5: =IFERROR(IF(INDEX(營收表現!H$6:H$3000,MATCH($A5,營收表現!$A$6:$A$3000,0))="","",INDEX(營收表現!H$6:H$3000,MATCH($A5,營收表現!$A$6:$A$3000,0))),"") -> 3.54 | J5: =IFERROR(IF(INDEX(營收表現!I$6:I$3000,MATCH($A5,營收表現!$A$6:$A$3000,0))="","",INDEX(營收表現!I$6:I$3000,MATCH($A5,營收表現!$A$6:$A$3000,0))),"") -> 31.89 | K5: =IFERROR(IF(INDEX(營收表現!J$6:J$3000,MATCH($A5,營收表現!$A$6:$A$3000,0))="","",INDEX(營收表現!J$6:J$3000,MATCH($A5,營收表現!$A$6:$A$3000,0))),"") -> 39.62 | ... N5: =IFERROR(IF(INDEX(營收表現!M$6:M$3000,MATCH($A5,營收表現!$A$6:$A$3000,0))="","",INDEX(營收表現!M$6:M$3000,MATCH($A5,營收表現!$A$6:$A$3000,0))),"") -> 33.04 | O5: =IF(INDEX(營收表現!N$6:N$3000,MATCH($A5,營收表現!$A$6:$A$3000,0))="","",INDEX(營收表現!N$6:N$3000,MATCH($A5,營收表現!$A$6:$A$3000,0))) -> 41.28
A6: 3680 | B6: =IFERROR(INDEX(營收表現!B$6:B$3000,MATCH($A6,營收表現!$A$6:$A$3000,0)),"") -> 家登 | C6: =IFERROR(INDEX(類別!G$4:G$3000,MATCH($A6,類別!$C$4:$C$3000,0)),"") -> 半導體設備 | D6: =IFERROR(IF(INDEX(營收表現!C$6:C$3000,MATCH($A6,營收表現!$A$6:$A$3000,0))="","",INDEX(營收表現!C$6:C$3000,MATCH($A6,營收表現!$A$6:$A$3000,0))),"") -> 10.4 | E6: =IFERROR(IF(INDEX(營收表現!D$6:D$3000,MATCH($A6,營收表現!$A$6:$A$3000,0))="","",INDEX(營收表現!D$6:D$3000,MATCH($A6,營收表現!$A$6:$A$3000,0))),"") -> 5.85 | F6: =IFERROR(IF(INDEX(營收表現!E$6:E$3000,MATCH($A6,營收表現!$A$6:$A$3000,0))="","",INDEX(營收表現!E$6:E$3000,MATCH($A6,營收表現!$A$6:$A$3000,0))),"") -> 11.11 | G6: =IFERROR(IF(INDEX(營收表現!F$6:F$3000,MATCH($A6,營收表現!$A$6:$A$3000,0))="","",INDEX(營收表現!F$6:F$3000,MATCH($A6,營收表現!$A$6:$A$3000,0))),"") -> 11.35 | H6: =IFERROR(IF(INDEX(營收表現!G$6:G$3000,MATCH($A6,營收表現!$A$6:$A$3000,0))="","",INDEX(營收表現!G$6:G$3000,MATCH($A6,營收表現!$A$6:$A$3000,0))),"") -> 19.07 | I6: =IFERROR(IF(INDEX(營收表現!H$6:H$3000,MATCH($A6,營收表現!$A$6:$A$3000,0))="","",INDEX(營收表現!H$6:H$3000,MATCH($A6,營收表現!$A$6:$A$3000,0))),"") -> -27.41 | J6: =IFERROR(IF(INDEX(營收表現!I$6:I$3000,MATCH($A6,營收表現!$A$6:$A$3000,0))="","",INDEX(營收表現!I$6:I$3000,MATCH($A6,營收表現!$A$6:$A$3000,0))),"") -> -13.3 | K6: =IFERROR(IF(INDEX(營收表現!J$6:J$3000,MATCH($A6,營收表現!$A$6:$A$3000,0))="","",INDEX(營收表現!J$6:J$3000,MATCH($A6,營收表現!$A$6:$A$3000,0))),"") -> -2.32 | ... N6: =IFERROR(IF(INDEX(營收表現!M$6:M$3000,MATCH($A6,營收表現!$A$6:$A$3000,0))="","",INDEX(營收表現!M$6:M$3000,MATCH($A6,營收表現!$A$6:$A$3000,0))),"") -> 49.17 | O6: =IF(INDEX(營收表現!N$6:N$3000,MATCH($A6,營收表現!$A$6:$A$3000,0))="","",INDEX(營收表現!N$6:N$3000,MATCH($A6,營收表現!$A$6:$A$3000,0))) -> 62.74
A7: 2308 | B7: =IFERROR(INDEX(營收表現!B$6:B$3000,MATCH($A7,營收表現!$A$6:$A$3000,0)),"") -> 台達電 | C7: =IFERROR(INDEX(類別!G$4:G$3000,MATCH($A7,類別!$C$4:$C$3000,0)),"") -> 供電與變壓 | D7: =IFERROR(IF(INDEX(營收表現!C$6:C$3000,MATCH($A7,營收表現!$A$6:$A$3000,0))="","",INDEX(營收表現!C$6:C$3000,MATCH($A7,營收表現!$A$6:$A$3000,0))),"") -> 5.42 | E7: =IFERROR(IF(INDEX(營收表現!D$6:D$3000,MATCH($A7,營收表現!$A$6:$A$3000,0))="","",INDEX(營收表現!D$6:D$3000,MATCH($A7,營收表現!$A$6:$A$3000,0))),"") -> 19.22 | F7: =IFERROR(IF(INDEX(營收表現!E$6:E$3000,MATCH($A7,營收表現!$A$6:$A$3000,0))="","",INDEX(營收表現!E$6:E$3000,MATCH($A7,營收表現!$A$6:$A$3000,0))),"") -> 0.57 | G7: =IFERROR(IF(INDEX(營收表現!F$6:F$3000,MATCH($A7,營收表現!$A$6:$A$3000,0))="","",INDEX(營收表現!F$6:F$3000,MATCH($A7,營收表現!$A$6:$A$3000,0))),"") -> -11.92 | H7: =IFERROR(IF(INDEX(營收表現!G$6:G$3000,MATCH($A7,營收表現!$A$6:$A$3000,0))="","",INDEX(營收表現!G$6:G$3000,MATCH($A7,營收表現!$A$6:$A$3000,0))),"") -> 6.22 | I7: =IFERROR(IF(INDEX(營收表現!H$6:H$3000,MATCH($A7,營收表現!$A$6:$A$3000,0))="","",INDEX(營收表現!H$6:H$3000,MATCH($A7,營收表現!$A$6:$A$3000,0))),"") -> -7.47 | J7: =IFERROR(IF(INDEX(營收表現!I$6:I$3000,MATCH($A7,營收表現!$A$6:$A$3000,0))="","",INDEX(營收表現!I$6:I$3000,MATCH($A7,營收表現!$A$6:$A$3000,0))),"") -> 26.71 | K7: =IFERROR(IF(INDEX(營收表現!J$6:J$3000,MATCH($A7,營收表現!$A$6:$A$3000,0))="","",INDEX(營收表現!J$6:J$3000,MATCH($A7,營收表現!$A$6:$A$3000,0))),"") -> 53.83 | ... N7: =IFERROR(IF(INDEX(營收表現!M$6:M$3000,MATCH($A7,營收表現!$A$6:$A$3000,0))="","",INDEX(營收表現!M$6:M$3000,MATCH($A7,營收表現!$A$6:$A$3000,0))),"") -> 38.59 | O7: =IF(INDEX(營收表現!N$6:N$3000,MATCH($A7,營收表現!$A$6:$A$3000,0))="","",INDEX(營收表現!N$6:N$3000,MATCH($A7,營收表現!$A$6:$A$3000,0))) -> 32.87
A8: 3711 | B8: =IFERROR(INDEX(營收表現!B$6:B$3000,MATCH($A8,營收表現!$A$6:$A$3000,0)),"") -> 日月光投控 | C8: =IFERROR(INDEX(類別!G$4:G$3000,MATCH($A8,類別!$C$4:$C$3000,0)),"") -> IC封測 | D8: =IFERROR(IF(INDEX(營收表現!C$6:C$3000,MATCH($A8,營收表現!$A$6:$A$3000,0))="","",INDEX(營收表現!C$6:C$3000,MATCH($A8,營收表現!$A$6:$A$3000,0))),"") -> 9.55 | E8: =IFERROR(IF(INDEX(營收表現!D$6:D$3000,MATCH($A8,營收表現!$A$6:$A$3000,0))="","",INDEX(營收表現!D$6:D$3000,MATCH($A8,營收表現!$A$6:$A$3000,0))),"") -> 7.25 | F8: =IFERROR(IF(INDEX(營收表現!E$6:E$3000,MATCH($A8,營收表現!$A$6:$A$3000,0))="","",INDEX(營收表現!E$6:E$3000,MATCH($A8,營收表現!$A$6:$A$3000,0))),"") -> -0.55 | G8: =IFERROR(IF(INDEX(營收表現!F$6:F$3000,MATCH($A8,營收表現!$A$6:$A$3000,0))="","",INDEX(營收表現!F$6:F$3000,MATCH($A8,營收表現!$A$6:$A$3000,0))),"") -> -2.34 | H8: =IFERROR(IF(INDEX(營收表現!G$6:G$3000,MATCH($A8,營收表現!$A$6:$A$3000,0))="","",INDEX(營收表現!G$6:G$3000,MATCH($A8,營收表現!$A$6:$A$3000,0))),"") -> 0.08 | I8: =IFERROR(IF(INDEX(營收表現!H$6:H$3000,MATCH($A8,營收表現!$A$6:$A$3000,0))="","",INDEX(營收表現!H$6:H$3000,MATCH($A8,營收表現!$A$6:$A$3000,0))),"") | J8: =IFERROR(IF(INDEX(營收表現!I$6:I$3000,MATCH($A8,營收表現!$A$6:$A$3000,0))="","",INDEX(營收表現!I$6:I$3000,MATCH($A8,營收表現!$A$6:$A$3000,0))),"") -> 6.68 | K8: =IFERROR(IF(INDEX(營收表現!J$6:J$3000,MATCH($A8,營收表現!$A$6:$A$3000,0))="","",INDEX(營收表現!J$6:J$3000,MATCH($A8,營收表現!$A$6:$A$3000,0))),"") -> 8.96 | ... N8: =IFERROR(IF(INDEX(營收表現!M$6:M$3000,MATCH($A8,營收表現!$A$6:$A$3000,0))="","",INDEX(營收表現!M$6:M$3000,MATCH($A8,營收表現!$A$6:$A$3000,0))),"") -> 11.27 | O8: =IF(INDEX(營收表現!N$6:N$3000,MATCH($A8,營收表現!$A$6:$A$3000,0))="","",INDEX(營收表現!N$6:N$3000,MATCH($A8,營收表現!$A$6:$A$3000,0)))
A9: 1711 | B9: =IFERROR(INDEX(營收表現!B$6:B$3000,MATCH($A9,營收表現!$A$6:$A$3000,0)),"") -> 永光 | C9: =IFERROR(INDEX(類別!G$4:G$3000,MATCH($A9,類別!$C$4:$C$3000,0)),"") -> 化工 | D9: =IFERROR(IF(INDEX(營收表現!C$6:C$3000,MATCH($A9,營收表現!$A$6:$A$3000,0))="","",INDEX(營收表現!C$6:C$3000,MATCH($A9,營收表現!$A$6:$A$3000,0))),"") -> -9.75 | E9: =IFERROR(IF(INDEX(營收表現!D$6:D$3000,MATCH($A9,營收表現!$A$6:$A$3000,0))="","",INDEX(營收表現!D$6:D$3000,MATCH($A9,營收表現!$A$6:$A$3000,0))),"") -> 11.09 | F9: =IFERROR(IF(INDEX(營收表現!E$6:E$3000,MATCH($A9,營收表現!$A$6:$A$3000,0))="","",INDEX(營收表現!E$6:E$3000,MATCH($A9,營收表現!$A$6:$A$3000,0))),"") -> -6.27 | G9: =IFERROR(IF(INDEX(營收表現!F$6:F$3000,MATCH($A9,營收表現!$A$6:$A$3000,0))="","",INDEX(營收表現!F$6:F$3000,MATCH($A9,營收表現!$A$6:$A$3000,0))),"") -> 1.06 | H9: =IFERROR(IF(INDEX(營收表現!G$6:G$3000,MATCH($A9,營收表現!$A$6:$A$3000,0))="","",INDEX(營收表現!G$6:G$3000,MATCH($A9,營收表現!$A$6:$A$3000,0))),"") -> 11.85 | I9: =IFERROR(IF(INDEX(營收表現!H$6:H$3000,MATCH($A9,營收表現!$A$6:$A$3000,0))="","",INDEX(營收表現!H$6:H$3000,MATCH($A9,營收表現!$A$6:$A$3000,0))),"") -> 9.7 | J9: =IFERROR(IF(INDEX(營收表現!I$6:I$3000,MATCH($A9,營收表現!$A$6:$A$3000,0))="","",INDEX(營收表現!I$6:I$3000,MATCH($A9,營收表現!$A$6:$A$3000,0))),"") -> -15.84 | K9: =IFERROR(IF(INDEX(營收表現!J$6:J$3000,MATCH($A9,營收表現!$A$6:$A$3000,0))="","",INDEX(營收表現!J$6:J$3000,MATCH($A9,營收表現!$A$6:$A$3000,0))),"") -> -7.71 | ... N9: =IFERROR(IF(INDEX(營收表現!M$6:M$3000,MATCH($A9,營收表現!$A$6:$A$3000,0))="","",INDEX(營收表現!M$6:M$3000,MATCH($A9,營收表現!$A$6:$A$3000,0))),"") -> -8.91 | O9: =IF(INDEX(營收表現!N$6:N$3000,MATCH($A9,營收表現!$A$6:$A$3000,0))="","",INDEX(營收表現!N$6:N$3000,MATCH($A9,營收表現!$A$6:$A$3000,0))) -> 12.74
A10: 1727 | B10: =IFERROR(INDEX(營收表現!B$6:B$3000,MATCH($A10,營收表現!$A$6:$A$3000,0)),"") -> 中華化 | C10: =IFERROR(INDEX(類別!G$4:G$3000,MATCH($A10,類別!$C$4:$C$3000,0)),"") -> 化工 | D10: =IFERROR(IF(INDEX(營收表現!C$6:C$3000,MATCH($A10,營收表現!$A$6:$A$3000,0))="","",INDEX(營收表現!C$6:C$3000,MATCH($A10,營收表現!$A$6:$A$3000,0))),"") -> -11.17 | E10: =IFERROR(IF(INDEX(營收表現!D$6:D$3000,MATCH($A10,營收表現!$A$6:$A$3000,0))="","",INDEX(營收表現!D$6:D$3000,MATCH($A10,營收表現!$A$6:$A$3000,0))),"") -> 14.12 | F10: =IFERROR(IF(INDEX(營收表現!E$6:E$3000,MATCH($A10,營收表現!$A$6:$A$3000,0))="","",INDEX(營收表現!E$6:E$3000,MATCH($A10,營收表現!$A$6:$A$3000,0))),"") -> -15.84 | G10: =IFERROR(IF(INDEX(營收表現!F$6:F$3000,MATCH($A10,營收表現!$A$6:$A$3000,0))="","",INDEX(營收表現!F$6:F$3000,MATCH($A10,營收表現!$A$6:$A$3000,0))),"") -> 14.21 | H10: =IFERROR(IF(INDEX(營收表現!G$6:G$3000,MATCH($A10,營收表現!$A$6:$A$3000,0))="","",INDEX(營收表現!G$6:G$3000,MATCH($A10,營收表現!$A$6:$A$3000,0))),"") -> -7.85 | I10: =IFERROR(IF(INDEX(營收表現!H$6:H$3000,MATCH($A10,營收表現!$A$6:$A$3000,0))="","",INDEX(營收表現!H$6:H$3000,MATCH($A10,營收表現!$A$6:$A$3000,0))),"") -> -25.5 | J10: =IFERROR(IF(INDEX(營收表現!I$6:I$3000,MATCH($A10,營收表現!$A$6:$A$3000,0))="","",INDEX(營收表現!I$6:I$3000,MATCH($A10,營收表現!$A$6:$A$3000,0))),"") -> -27.8 | K10: =IFERROR(IF(INDEX(營收表現!J$6:J$3000,MATCH($A10,營收表現!$A$6:$A$3000,0))="","",INDEX(營收表現!J$6:J$3000,MATCH($A10,營收表現!$A$6:$A$3000,0))),"") -> -10.9 | ... N10: =IFERROR(IF(INDEX(營收表現!M$6:M$3000,MATCH($A10,營收表現!$A$6:$A$3000,0))="","",INDEX(營收表現!M$6:M$3000,MATCH($A10,營收表現!$A$6:$A$3000,0))),"") -> 25.08 | O10: =IF(INDEX(營收表現!N$6:N$3000,MATCH($A10,營收表現!$A$6:$A$3000,0))="","",INDEX(營收表現!N$6:N$3000,MATCH($A10,營收表現!$A$6:$A$3000,0))) -> -9.74
A11: 1717 | B11: =IFERROR(INDEX(營收表現!B$6:B$3000,MATCH($A11,營收表現!$A$6:$A$3000,0)),"") -> 長興 | C11: =IFERROR(INDEX(類別!G$4:G$3000,MATCH($A11,類別!$C$4:$C$3000,0)),"") -> 化工 | D11: =IFERROR(IF(INDEX(營收表現!C$6:C$3000,MATCH($A11,營收表現!$A$6:$A$3000,0))="","",INDEX(營收表現!C$6:C$3000,MATCH($A11,營收表現!$A$6:$A$3000,0))),"") -> 1.83 | E11: =IFERROR(IF(INDEX(營收表現!D$6:D$3000,MATCH($A11,營收表現!$A$6:$A$3000,0))="","",INDEX(營收表現!D$6:D$3000,MATCH($A11,營收表現!$A$6:$A$3000,0))),"") -> 1.85 | F11: =IFERROR(IF(INDEX(營收表現!E$6:E$3000,MATCH($A11,營收表現!$A$6:$A$3000,0))="","",INDEX(營收表現!E$6:E$3000,MATCH($A11,營收表現!$A$6:$A$3000,0))),"") -> -9.48 | G11: =IFERROR(IF(INDEX(營收表現!F$6:F$3000,MATCH($A11,營收表現!$A$6:$A$3000,0))="","",INDEX(營收表現!F$6:F$3000,MATCH($A11,營收表現!$A$6:$A$3000,0))),"") -> 6.29 | H11: =IFERROR(IF(INDEX(營收表現!G$6:G$3000,MATCH($A11,營收表現!$A$6:$A$3000,0))="","",INDEX(營收表現!G$6:G$3000,MATCH($A11,營收表現!$A$6:$A$3000,0))),"") -> 12.93 | I11: =IFERROR(IF(INDEX(營收表現!H$6:H$3000,MATCH($A11,營收表現!$A$6:$A$3000,0))="","",INDEX(營收表現!H$6:H$3000,MATCH($A11,營收表現!$A$6:$A$3000,0))),"") -> 4.45 | J11: =IFERROR(IF(INDEX(營收表現!I$6:I$3000,MATCH($A11,營收表現!$A$6:$A$3000,0))="","",INDEX(營收表現!I$6:I$3000,MATCH($A11,營收表現!$A$6:$A$3000,0))),"") -> -15.01 | K11: =IFERROR(IF(INDEX(營收表現!J$6:J$3000,MATCH($A11,營收表現!$A$6:$A$3000,0))="","",INDEX(營收表現!J$6:J$3000,MATCH($A11,營收表現!$A$6:$A$3000,0))),"") -> -5.28 | ... N11: =IFERROR(IF(INDEX(營收表現!M$6:M$3000,MATCH($A11,營收表現!$A$6:$A$3000,0))="","",INDEX(營收表現!M$6:M$3000,MATCH($A11,營收表現!$A$6:$A$3000,0))),"") -> -6.17 | O11: =IF(INDEX(營收表現!N$6:N$3000,MATCH($A11,營收表現!$A$6:$A$3000,0))="","",INDEX(營收表現!N$6:N$3000,MATCH($A11,營收表現!$A$6:$A$3000,0))) -> 16.98
A12: 6239 | B12: =IFERROR(INDEX(營收表現!B$6:B$3000,MATCH($A12,營收表現!$A$6:$A$3000,0)),"") -> 力成 | C12: =IFERROR(INDEX(類別!G$4:G$3000,MATCH($A12,類別!$C$4:$C$3000,0)),"") -> IC封測 | D12: =IFERROR(IF(INDEX(營收表現!C$6:C$3000,MATCH($A12,營收表現!$A$6:$A$3000,0))="","",INDEX(營收表現!C$6:C$3000,MATCH($A12,營收表現!$A$6:$A$3000,0))),"") -> 7.56 | E12: =IFERROR(IF(INDEX(營收表現!D$6:D$3000,MATCH($A12,營收表現!$A$6:$A$3000,0))="","",INDEX(營收表現!D$6:D$3000,MATCH($A12,營收表現!$A$6:$A$3000,0))),"") -> -2.56 | F12: =IFERROR(IF(INDEX(營收表現!E$6:E$3000,MATCH($A12,營收表現!$A$6:$A$3000,0))="","",INDEX(營收表現!E$6:E$3000,MATCH($A12,營收表現!$A$6:$A$3000,0))),"") -> 4.04 | G12: =IFERROR(IF(INDEX(營收表現!F$6:F$3000,MATCH($A12,營收表現!$A$6:$A$3000,0))="","",INDEX(營收表現!F$6:F$3000,MATCH($A12,營收表現!$A$6:$A$3000,0))),"") -> 2.43 | H12: =IFERROR(IF(INDEX(營收表現!G$6:G$3000,MATCH($A12,營收表現!$A$6:$A$3000,0))="","",INDEX(營收表現!G$6:G$3000,MATCH($A12,營收表現!$A$6:$A$3000,0))),"") -> 2.19 | I12: =IFERROR(IF(INDEX(營收表現!H$6:H$3000,MATCH($A12,營收表現!$A$6:$A$3000,0))="","",INDEX(營收表現!H$6:H$3000,MATCH($A12,營收表現!$A$6:$A$3000,0))),"") -> -0.74 | J12: =IFERROR(IF(INDEX(營收表現!I$6:I$3000,MATCH($A12,營收表現!$A$6:$A$3000,0))="","",INDEX(營收表現!I$6:I$3000,MATCH($A12,營收表現!$A$6:$A$3000,0))),"") -> 8.68 | K12: =IFERROR(IF(INDEX(營收表現!J$6:J$3000,MATCH($A12,營收表現!$A$6:$A$3000,0))="","",INDEX(營收表現!J$6:J$3000,MATCH($A12,營收表現!$A$6:$A$3000,0))),"") -> 17.42 | ... N12: =IFERROR(IF(INDEX(營收表現!M$6:M$3000,MATCH($A12,營收表現!$A$6:$A$3000,0))="","",INDEX(營收表現!M$6:M$3000,MATCH($A12,營收表現!$A$6:$A$3000,0))),"") -> 30.52 | O12: =IF(INDEX(營收表現!N$6:N$3000,MATCH($A12,營收表現!$A$6:$A$3000,0))="","",INDEX(營收表現!N$6:N$3000,MATCH($A12,營收表現!$A$6:$A$3000,0))) -> 43.04
A13: 9933 | B13: =IFERROR(INDEX(營收表現!B$6:B$3000,MATCH($A13,營收表現!$A$6:$A$3000,0)),"") -> 中鼎 | C13: =IFERROR(INDEX(類別!G$4:G$3000,MATCH($A13,類別!$C$4:$C$3000,0)),"") -> 公共工程 | D13: =IFERROR(IF(INDEX(營收表現!C$6:C$3000,MATCH($A13,營收表現!$A$6:$A$3000,0))="","",INDEX(營收表現!C$6:C$3000,MATCH($A13,營收表現!$A$6:$A$3000,0))),"") -> 1.51 | E13: =IFERROR(IF(INDEX(營收表現!D$6:D$3000,MATCH($A13,營收表現!$A$6:$A$3000,0))="","",INDEX(營收表現!D$6:D$3000,MATCH($A13,營收表現!$A$6:$A$3000,0))),"") -> 20.59 | F13: =IFERROR(IF(INDEX(營收表現!E$6:E$3000,MATCH($A13,營收表現!$A$6:$A$3000,0))="","",INDEX(營收表現!E$6:E$3000,MATCH($A13,營收表現!$A$6:$A$3000,0))),"") -> -26.84 | G13: =IFERROR(IF(INDEX(營收表現!F$6:F$3000,MATCH($A13,營收表現!$A$6:$A$3000,0))="","",INDEX(營收表現!F$6:F$3000,MATCH($A13,營收表現!$A$6:$A$3000,0))),"") -> 15.03 | H13: =IFERROR(IF(INDEX(營收表現!G$6:G$3000,MATCH($A13,營收表現!$A$6:$A$3000,0))="","",INDEX(營收表現!G$6:G$3000,MATCH($A13,營收表現!$A$6:$A$3000,0))),"") -> 71.36 | I13: =IFERROR(IF(INDEX(營收表現!H$6:H$3000,MATCH($A13,營收表現!$A$6:$A$3000,0))="","",INDEX(營收表現!H$6:H$3000,MATCH($A13,營收表現!$A$6:$A$3000,0))),"") -> -51.5 | J13: =IFERROR(IF(INDEX(營收表現!I$6:I$3000,MATCH($A13,營收表現!$A$6:$A$3000,0))="","",INDEX(營收表現!I$6:I$3000,MATCH($A13,營收表現!$A$6:$A$3000,0))),"") -> -33 | K13: =IFERROR(IF(INDEX(營收表現!J$6:J$3000,MATCH($A13,營收表現!$A$6:$A$3000,0))="","",INDEX(營收表現!J$6:J$3000,MATCH($A13,營收表現!$A$6:$A$3000,0))),"") -> -11.7 | ... N13: =IFERROR(IF(INDEX(營收表現!M$6:M$3000,MATCH($A13,營收表現!$A$6:$A$3000,0))="","",INDEX(營收表現!M$6:M$3000,MATCH($A13,營收表現!$A$6:$A$3000,0))),"") -> -15.29 | O13: =IF(INDEX(營收表現!N$6:N$3000,MATCH($A13,營收表現!$A$6:$A$3000,0))="","",INDEX(營收表現!N$6:N$3000,MATCH($A13,營收表現!$A$6:$A$3000,0))) -> -4.74
... A68: 4306 | B68: =IFERROR(INDEX(營收表現!B$6:B$3000,MATCH($A68,營收表現!$A$6:$A$3000,0)),"") -> 炎洲 | C68: =IFERROR(INDEX(類別!G$4:G$3000,MATCH($A68,類別!$C$4:$C$3000,0)),"") -> 塑膠 | D68: =IFERROR(IF(INDEX(營收表現!C$6:C$3000,MATCH($A68,營收表現!$A$6:$A$3000,0))="","",INDEX(營收表現!C$6:C$3000,MATCH($A68,營收表現!$A$6:$A$3000,0))),"") -> 3.04 | E68: =IFERROR(IF(INDEX(營收表現!D$6:D$3000,MATCH($A68,營收表現!$A$6:$A$3000,0))="","",INDEX(營收表現!D$6:D$3000,MATCH($A68,營收表現!$A$6:$A$3000,0))),"") -> 2.54 | F68: =IFERROR(IF(INDEX(營收表現!E$6:E$3000,MATCH($A68,營收表現!$A$6:$A$3000,0))="","",INDEX(營收表現!E$6:E$3000,MATCH($A68,營收表現!$A$6:$A$3000,0))),"") -> -0.06 | G68: =IFERROR(IF(INDEX(營收表現!F$6:F$3000,MATCH($A68,營收表現!$A$6:$A$3000,0))="","",INDEX(營收表現!F$6:F$3000,MATCH($A68,營收表現!$A$6:$A$3000,0))),"") -> 13.29 | H68: =IFERROR(IF(INDEX(營收表現!G$6:G$3000,MATCH($A68,營收表現!$A$6:$A$3000,0))="","",INDEX(營收表現!G$6:G$3000,MATCH($A68,營收表現!$A$6:$A$3000,0))),"") -> -4.86 | I68: =IFERROR(IF(INDEX(營收表現!H$6:H$3000,MATCH($A68,營收表現!$A$6:$A$3000,0))="","",INDEX(營收表現!H$6:H$3000,MATCH($A68,營收表現!$A$6:$A$3000,0))),"") -> -2.72 | J68: =IFERROR(IF(INDEX(營收表現!I$6:I$3000,MATCH($A68,營收表現!$A$6:$A$3000,0))="","",INDEX(營收表現!I$6:I$3000,MATCH($A68,營收表現!$A$6:$A$3000,0))),"") -> -21.08 | K68: =IFERROR(IF(INDEX(營收表現!J$6:J$3000,MATCH($A68,營收表現!$A$6:$A$3000,0))="","",INDEX(營收表現!J$6:J$3000,MATCH($A68,營收表現!$A$6:$A$3000,0))),"") -> -9.4 | ... N68: =IFERROR(IF(INDEX(營收表現!M$6:M$3000,MATCH($A68,營收表現!$A$6:$A$3000,0))="","",INDEX(營收表現!M$6:M$3000,MATCH($A68,營收表現!$A$6:$A$3000,0))),"") -> 11.94 | O68: =IF(INDEX(營收表現!N$6:N$3000,MATCH($A68,營收表現!$A$6:$A$3000,0))="","",INDEX(營收表現!N$6:N$3000,MATCH($A68,營收表現!$A$6:$A$3000,0))) -> 29.1
B69: =IFERROR(INDEX(營收表現!B$6:B$3000,MATCH($A69,營收表現!$A$6:$A$3000,0)),"") | C69: =IFERROR(INDEX(類別!G$4:G$3000,MATCH($A69,類別!$C$4:$C$3000,0)),"") | D69: =IFERROR(IF(INDEX(營收表現!C$6:C$3000,MATCH($A69,營收表現!$A$6:$A$3000,0))="","",INDEX(營收表現!C$6:C$3000,MATCH($A69,營收表現!$A$6:$A$3000,0))),"") | E69: =IFERROR(IF(INDEX(營收表現!D$6:D$3000,MATCH($A69,營收表現!$A$6:$A$3000,0))="","",INDEX(營收表現!D$6:D$3000,MATCH($A69,營收表現!$A$6:$A$3000,0))),"") | F69: =IFERROR(IF(INDEX(營收表現!E$6:E$3000,MATCH($A69,營收表現!$A$6:$A$3000,0))="","",INDEX(營收表現!E$6:E$3000,MATCH($A69,營收表現!$A$6:$A$3000,0))),"") | G69: =IFERROR(IF(INDEX(營收表現!F$6:F$3000,MATCH($A69,營收表現!$A$6:$A$3000,0))="","",INDEX(營收表現!F$6:F$3000,MATCH($A69,營收表現!$A$6:$A$3000,0))),"") | H69: =IFERROR(IF(INDEX(營收表現!G$6:G$3000,MATCH($A69,營收表現!$A$6:$A$3000,0))="","",INDEX(營收表現!G$6:G$3000,MATCH($A69,營收表現!$A$6:$A$3000,0))),"") | I69: =IFERROR(IF(INDEX(營收表現!H$6:H$3000,MATCH($A69,營收表現!$A$6:$A$3000,0))="","",INDEX(營收表現!H$6:H$3000,MATCH($A69,營收表現!$A$6:$A$3000,0))),"") | J69: =IFERROR(IF(INDEX(營收表現!I$6:I$3000,MATCH($A69,營收表現!$A$6:$A$3000,0))="","",INDEX(營收表現!I$6:I$3000,MATCH($A69,營收表現!$A$6:$A$3000,0))),"") | K69: =IFERROR(IF(INDEX(營收表現!J$6:J$3000,MATCH($A69,營收表現!$A$6:$A$3000,0))="","",INDEX(營收表現!J$6:J$3000,MATCH($A69,營收表現!$A$6:$A$3000,0))),"") | ... O69: =IFERROR(IF(INDEX(營收表現!N$6:N$3000,MATCH($A69,營收表現!$A$6:$A$3000,0))="","",INDEX(營收表現!N$6:N$3000,MATCH($A69,營收表現!$A$6:$A$3000,0))),"")
B70: =IFERROR(INDEX(營收表現!B$6:B$3000,MATCH($A70,營收表現!$A$6:$A$3000,0)),"") | C70: =IFERROR(INDEX(類別!G$4:G$3000,MATCH($A70,類別!$C$4:$C$3000,0)),"") | D70: =IFERROR(IF(INDEX(營收表現!C$6:C$3000,MATCH($A70,營收表現!$A$6:$A$3000,0))="","",INDEX(營收表現!C$6:C$3000,MATCH($A70,營收表現!$A$6:$A$3000,0))),"") | E70: =IFERROR(IF(INDEX(營收表現!D$6:D$3000,MATCH($A70,營收表現!$A$6:$A$3000,0))="","",INDEX(營收表現!D$6:D$3000,MATCH($A70,營收表現!$A$6:$A$3000,0))),"") | F70: =IFERROR(IF(INDEX(營收表現!E$6:E$3000,MATCH($A70,營收表現!$A$6:$A$3000,0))="","",INDEX(營收表現!E$6:E$3000,MATCH($A70,營收表現!$A$6:$A$3000,0))),"") | G70: =IFERROR(IF(INDEX(營收表現!F$6:F$3000,MATCH($A70,營收表現!$A$6:$A$3000,0))="","",INDEX(營收表現!F$6:F$3000,MATCH($A70,營收表現!$A$6:$A$3000,0))),"") | H70: =IFERROR(IF(INDEX(營收表現!G$6:G$3000,MATCH($A70,營收表現!$A$6:$A$3000,0))="","",INDEX(營收表現!G$6:G$3000,MATCH($A70,營收表現!$A$6:$A$3000,0))),"") | I70: =IFERROR(IF(INDEX(營收表現!H$6:H$3000,MATCH($A70,營收表現!$A$6:$A$3000,0))="","",INDEX(營收表現!H$6:H$3000,MATCH($A70,營收表現!$A$6:$A$3000,0))),"") | J70: =IFERROR(IF(INDEX(營收表現!I$6:I$3000,MATCH($A70,營收表現!$A$6:$A$3000,0))="","",INDEX(營收表現!I$6:I$3000,MATCH($A70,營收表現!$A$6:$A$3000,0))),"") | K70: =IFERROR(IF(INDEX(營收表現!J$6:J$3000,MATCH($A70,營收表現!$A$6:$A$3000,0))="","",INDEX(營收表現!J$6:J$3000,MATCH($A70,營收表現!$A$6:$A$3000,0))),"") | ... O70: =IFERROR(IF(INDEX(營收表現!N$6:N$3000,MATCH($A70,營收表現!$A$6:$A$3000,0))="","",INDEX(營收表現!N$6:N$3000,MATCH($A70,營收表現!$A$6:$A$3000,0))),"")
B71: =IFERROR(INDEX(營收表現!B$6:B$3000,MATCH($A71,營收表現!$A$6:$A$3000,0)),"") | C71: =IFERROR(INDEX(類別!G$4:G$3000,MATCH($A71,類別!$C$4:$C$3000,0)),"") | D71: =IFERROR(IF(INDEX(營收表現!C$6:C$3000,MATCH($A71,營收表現!$A$6:$A$3000,0))="","",INDEX(營收表現!C$6:C$3000,MATCH($A71,營收表現!$A$6:$A$3000,0))),"") | E71: =IFERROR(IF(INDEX(營收表現!D$6:D$3000,MATCH($A71,營收表現!$A$6:$A$3000,0))="","",INDEX(營收表現!D$6:D$3000,MATCH($A71,營收表現!$A$6:$A$3000,0))),"") | F71: =IFERROR(IF(INDEX(營收表現!E$6:E$3000,MATCH($A71,營收表現!$A$6:$A$3000,0))="","",INDEX(營收表現!E$6:E$3000,MATCH($A71,營收表現!$A$6:$A$3000,0))),"") | G71: =IFERROR(IF(INDEX(營收表現!F$6:F$3000,MATCH($A71,營收表現!$A$6:$A$3000,0))="","",INDEX(營收表現!F$6:F$3000,MATCH($A71,營收表現!$A$6:$A$3000,0))),"") | H71: =IFERROR(IF(INDEX(營收表現!G$6:G$3000,MATCH($A71,營收表現!$A$6:$A$3000,0))="","",INDEX(營收表現!G$6:G$3000,MATCH($A71,營收表現!$A$6:$A$3000,0))),"") | I71: =IFERROR(IF(INDEX(營收表現!H$6:H$3000,MATCH($A71,營收表現!$A$6:$A$3000,0))="","",INDEX(營收表現!H$6:H$3000,MATCH($A71,營收表現!$A$6:$A$3000,0))),"") | J71: =IFERROR(IF(INDEX(營收表現!I$6:I$3000,MATCH($A71,營收表現!$A$6:$A$3000,0))="","",INDEX(營收表現!I$6:I$3000,MATCH($A71,營收表現!$A$6:$A$3000,0))),"") | K71: =IFERROR(IF(INDEX(營收表現!J$6:J$3000,MATCH($A71,營收表現!$A$6:$A$3000,0))="","",INDEX(營收表現!J$6:J$3000,MATCH($A71,營收表現!$A$6:$A$3000,0))),"") | ... O71: =IFERROR(IF(INDEX(營收表現!N$6:N$3000,MATCH($A71,營收表現!$A$6:$A$3000,0))="","",INDEX(營收表現!N$6:N$3000,MATCH($A71,營收表現!$A$6:$A$3000,0))),"")
B72: =IFERROR(INDEX(營收表現!B$6:B$3000,MATCH($A72,營收表現!$A$6:$A$3000,0)),"") | C72: =IFERROR(INDEX(類別!G$4:G$3000,MATCH($A72,類別!$C$4:$C$3000,0)),"") | D72: =IFERROR(IF(INDEX(營收表現!C$6:C$3000,MATCH($A72,營收表現!$A$6:$A$3000,0))="","",INDEX(營收表現!C$6:C$3000,MATCH($A72,營收表現!$A$6:$A$3000,0))),"") | E72: =IFERROR(IF(INDEX(營收表現!D$6:D$3000,MATCH($A72,營收表現!$A$6:$A$3000,0))="","",INDEX(營收表現!D$6:D$3000,MATCH($A72,營收表現!$A$6:$A$3000,0))),"") | F72: =IFERROR(IF(INDEX(營收表現!E$6:E$3000,MATCH($A72,營收表現!$A$6:$A$3000,0))="","",INDEX(營收表現!E$6:E$3000,MATCH($A72,營收表現!$A$6:$A$3000,0))),"") | G72: =IFERROR(IF(INDEX(營收表現!F$6:F$3000,MATCH($A72,營收表現!$A$6:$A$3000,0))="","",INDEX(營收表現!F$6:F$3000,MATCH($A72,營收表現!$A$6:$A$3000,0))),"") | H72: =IFERROR(IF(INDEX(營收表現!G$6:G$3000,MATCH($A72,營收表現!$A$6:$A$3000,0))="","",INDEX(營收表現!G$6:G$3000,MATCH($A72,營收表現!$A$6:$A$3000,0))),"") | I72: =IFERROR(IF(INDEX(營收表現!H$6:H$3000,MATCH($A72,營收表現!$A$6:$A$3000,0))="","",INDEX(營收表現!H$6:H$3000,MATCH($A72,營收表現!$A$6:$A$3000,0))),"") | J72: =IFERROR(IF(INDEX(營收表現!I$6:I$3000,MATCH($A72,營收表現!$A$6:$A$3000,0))="","",INDEX(營收表現!I$6:I$3000,MATCH($A72,營收表現!$A$6:$A$3000,0))),"") | K72: =IFERROR(IF(INDEX(營收表現!J$6:J$3000,MATCH($A72,營收表現!$A$6:$A$3000,0))="","",INDEX(營收表現!J$6:J$3000,MATCH($A72,營收表現!$A$6:$A$3000,0))),"") | ... O72: =IFERROR(IF(INDEX(營收表現!N$6:N$3000,MATCH($A72,營收表現!$A$6:$A$3000,0))="","",INDEX(營收表現!N$6:N$3000,MATCH($A72,營收表現!$A$6:$A$3000,0))),"")
B73: =IFERROR(INDEX(營收表現!B$6:B$3000,MATCH($A73,營收表現!$A$6:$A$3000,0)),"") | C73: =IFERROR(INDEX(類別!G$4:G$3000,MATCH($A73,類別!$C$4:$C$3000,0)),"") | D73: =IFERROR(IF(INDEX(營收表現!C$6:C$3000,MATCH($A73,營收表現!$A$6:$A$3000,0))="","",INDEX(營收表現!C$6:C$3000,MATCH($A73,營收表現!$A$6:$A$3000,0))),"") | E73: =IFERROR(IF(INDEX(營收表現!D$6:D$3000,MATCH($A73,營收表現!$A$6:$A$3000,0))="","",INDEX(營收表現!D$6:D$3000,MATCH($A73,營收表現!$A$6:$A$3000,0))),"") | F73: =IFERROR(IF(INDEX(營收表現!E$6:E$3000,MATCH($A73,營收表現!$A$6:$A$3000,0))="","",INDEX(營收表現!E$6:E$3000,MATCH($A73,營收表現!$A$6:$A$3000,0))),"") | G73: =IFERROR(IF(INDEX(營收表現!F$6:F$3000,MATCH($A73,營收表現!$A$6:$A$3000,0))="","",INDEX(營收表現!F$6:F$3000,MATCH($A73,營收表現!$A$6:$A$3000,0))),"") | H73: =IFERROR(IF(INDEX(營收表現!G$6:G$3000,MATCH($A73,營收表現!$A$6:$A$3000,0))="","",INDEX(營收表現!G$6:G$3000,MATCH($A73,營收表現!$A$6:$A$3000,0))),"") | I73: =IFERROR(IF(INDEX(營收表現!H$6:H$3000,MATCH($A73,營收表現!$A$6:$A$3000,0))="","",INDEX(營收表現!H$6:H$3000,MATCH($A73,營收表現!$A$6:$A$3000,0))),"") | J73: =IFERROR(IF(INDEX(營收表現!I$6:I$3000,MATCH($A73,營收表現!$A$6:$A$3000,0))="","",INDEX(營收表現!I$6:I$3000,MATCH($A73,營收表現!$A$6:$A$3000,0))),"") | K73: =IFERROR(IF(INDEX(營收表現!J$6:J$3000,MATCH($A73,營收表現!$A$6:$A$3000,0))="","",INDEX(營收表現!J$6:J$3000,MATCH($A73,營收表現!$A$6:$A$3000,0))),"") | ... O73: =IFERROR(IF(INDEX(營收表現!N$6:N$3000,MATCH($A73,營收表現!$A$6:$A$3000,0))="","",INDEX(營收表現!N$6:N$3000,MATCH($A73,營收表現!$A$6:$A$3000,0))),"")
B74: =IFERROR(INDEX(營收表現!B$6:B$3000,MATCH($A74,營收表現!$A$6:$A$3000,0)),"") | C74: =IFERROR(INDEX(類別!G$4:G$3000,MATCH($A74,類別!$C$4:$C$3000,0)),"") | D74: =IFERROR(IF(INDEX(營收表現!C$6:C$3000,MATCH($A74,營收表現!$A$6:$A$3000,0))="","",INDEX(營收表現!C$6:C$3000,MATCH($A74,營收表現!$A$6:$A$3000,0))),"") | E74: =IFERROR(IF(INDEX(營收表現!D$6:D$3000,MATCH($A74,營收表現!$A$6:$A$3000,0))="","",INDEX(營收表現!D$6:D$3000,MATCH($A74,營收表現!$A$6:$A$3000,0))),"") | F74: =IFERROR(IF(INDEX(營收表現!E$6:E$3000,MATCH($A74,營收表現!$A$6:$A$3000,0))="","",INDEX(營收表現!E$6:E$3000,MATCH($A74,營收表現!$A$6:$A$3000,0))),"") | G74: =IFERROR(IF(INDEX(營收表現!F$6:F$3000,MATCH($A74,營收表現!$A$6:$A$3000,0))="","",INDEX(營收表現!F$6:F$3000,MATCH($A74,營收表現!$A$6:$A$3000,0))),"") | H74: =IFERROR(IF(INDEX(營收表現!G$6:G$3000,MATCH($A74,營收表現!$A$6:$A$3000,0))="","",INDEX(營收表現!G$6:G$3000,MATCH($A74,營收表現!$A$6:$A$3000,0))),"") | I74: =IFERROR(IF(INDEX(營收表現!H$6:H$3000,MATCH($A74,營收表現!$A$6:$A$3000,0))="","",INDEX(營收表現!H$6:H$3000,MATCH($A74,營收表現!$A$6:$A$3000,0))),"") | J74: =IFERROR(IF(INDEX(營收表現!I$6:I$3000,MATCH($A74,營收表現!$A$6:$A$3000,0))="","",INDEX(營收表現!I$6:I$3000,MATCH($A74,營收表現!$A$6:$A$3000,0))),"") | K74: =IFERROR(IF(INDEX(營收表現!J$6:J$3000,MATCH($A74,營收表現!$A$6:$A$3000,0))="","",INDEX(營收表現!J$6:J$3000,MATCH($A74,營收表現!$A$6:$A$3000,0))),"") | ... O74: =IFERROR(IF(INDEX(營收表現!N$6:N$3000,MATCH($A74,營收表現!$A$6:$A$3000,0))="","",INDEX(營收表現!N$6:N$3000,MATCH($A74,營收表現!$A$6:$A$3000,0))),"")
B75: =IFERROR(INDEX(營收表現!B$6:B$3000,MATCH($A75,營收表現!$A$6:$A$3000,0)),"") | C75: =IFERROR(INDEX(類別!G$4:G$3000,MATCH($A75,類別!$C$4:$C$3000,0)),"") | D75: =IFERROR(IF(INDEX(營收表現!C$6:C$3000,MATCH($A75,營收表現!$A$6:$A$3000,0))="","",INDEX(營收表現!C$6:C$3000,MATCH($A75,營收表現!$A$6:$A$3000,0))),"") | E75: =IFERROR(IF(INDEX(營收表現!D$6:D$3000,MATCH($A75,營收表現!$A$6:$A$3000,0))="","",INDEX(營收表現!D$6:D$3000,MATCH($A75,營收表現!$A$6:$A$3000,0))),"") | F75: =IFERROR(IF(INDEX(營收表現!E$6:E$3000,MATCH($A75,營收表現!$A$6:$A$3000,0))="","",INDEX(營收表現!E$6:E$3000,MATCH($A75,營收表現!$A$6:$A$3000,0))),"") | G75: =IFERROR(IF(INDEX(營收表現!F$6:F$3000,MATCH($A75,營收表現!$A$6:$A$3000,0))="","",INDEX(營收表現!F$6:F$3000,MATCH($A75,營收表現!$A$6:$A$3000,0))),"") | H75: =IFERROR(IF(INDEX(營收表現!G$6:G$3000,MATCH($A75,營收表現!$A$6:$A$3000,0))="","",INDEX(營收表現!G$6:G$3000,MATCH($A75,營收表現!$A$6:$A$3000,0))),"") | I75: =IFERROR(IF(INDEX(營收表現!H$6:H$3000,MATCH($A75,營收表現!$A$6:$A$3000,0))="","",INDEX(營收表現!H$6:H$3000,MATCH($A75,營收表現!$A$6:$A$3000,0))),"") | J75: =IFERROR(IF(INDEX(營收表現!I$6:I$3000,MATCH($A75,營收表現!$A$6:$A$3000,0))="","",INDEX(營收表現!I$6:I$3000,MATCH($A75,營收表現!$A$6:$A$3000,0))),"") | K75: =IFERROR(IF(INDEX(營收表現!J$6:J$3000,MATCH($A75,營收表現!$A$6:$A$3000,0))="","",INDEX(營收表現!J$6:J$3000,MATCH($A75,營收表現!$A$6:$A$3000,0))),"") | ... O75: =IFERROR(IF(INDEX(營收表現!N$6:N$3000,MATCH($A75,營收表現!$A$6:$A$3000,0))="","",INDEX(營收表現!N$6:N$3000,MATCH($A75,營收表現!$A$6:$A$3000,0))),"")
B76: =IFERROR(INDEX(營收表現!B$6:B$3000,MATCH($A76,營收表現!$A$6:$A$3000,0)),"") | C76: =IFERROR(INDEX(類別!G$4:G$3000,MATCH($A76,類別!$C$4:$C$3000,0)),"") | D76: =IFERROR(IF(INDEX(營收表現!C$6:C$3000,MATCH($A76,營收表現!$A$6:$A$3000,0))="","",INDEX(營收表現!C$6:C$3000,MATCH($A76,營收表現!$A$6:$A$3000,0))),"") | E76: =IFERROR(IF(INDEX(營收表現!D$6:D$3000,MATCH($A76,營收表現!$A$6:$A$3000,0))="","",INDEX(營收表現!D$6:D$3000,MATCH($A76,營收表現!$A$6:$A$3000,0))),"") | F76: =IFERROR(IF(INDEX(營收表現!E$6:E$3000,MATCH($A76,營收表現!$A$6:$A$3000,0))="","",INDEX(營收表現!E$6:E$3000,MATCH($A76,營收表現!$A$6:$A$3000,0))),"") | G76: =IFERROR(IF(INDEX(營收表現!F$6:F$3000,MATCH($A76,營收表現!$A$6:$A$3000,0))="","",INDEX(營收表現!F$6:F$3000,MATCH($A76,營收表現!$A$6:$A$3000,0))),"") | H76: =IFERROR(IF(INDEX(營收表現!G$6:G$3000,MATCH($A76,營收表現!$A$6:$A$3000,0))="","",INDEX(營收表現!G$6:G$3000,MATCH($A76,營收表現!$A$6:$A$3000,0))),"") | I76: =IFERROR(IF(INDEX(營收表現!H$6:H$3000,MATCH($A76,營收表現!$A$6:$A$3000,0))="","",INDEX(營收表現!H$6:H$3000,MATCH($A76,營收表現!$A$6:$A$3000,0))),"") | J76: =IFERROR(IF(INDEX(營收表現!I$6:I$3000,MATCH($A76,營收表現!$A$6:$A$3000,0))="","",INDEX(營收表現!I$6:I$3000,MATCH($A76,營收表現!$A$6:$A$3000,0))),"") | K76: =IFERROR(IF(INDEX(營收表現!J$6:J$3000,MATCH($A76,營收表現!$A$6:$A$3000,0))="","",INDEX(營收表現!J$6:J$3000,MATCH($A76,營收表現!$A$6:$A$3000,0))),"") | ... O76: =IFERROR(IF(INDEX(營收表現!N$6:N$3000,MATCH($A76,營收表現!$A$6:$A$3000,0))="","",INDEX(營收表現!N$6:N$3000,MATCH($A76,營收表現!$A$6:$A$3000,0))),"")
B77: =IFERROR(INDEX(營收表現!B$6:B$3000,MATCH($A77,營收表現!$A$6:$A$3000,0)),"") | C77: =IFERROR(INDEX(類別!G$4:G$3000,MATCH($A77,類別!$C$4:$C$3000,0)),"") | D77: =IFERROR(IF(INDEX(營收表現!C$6:C$3000,MATCH($A77,營收表現!$A$6:$A$3000,0))="","",INDEX(營收表現!C$6:C$3000,MATCH($A77,營收表現!$A$6:$A$3000,0))),"") | E77: =IFERROR(IF(INDEX(營收表現!D$6:D$3000,MATCH($A77,營收表現!$A$6:$A$3000,0))="","",INDEX(營收表現!D$6:D$3000,MATCH($A77,營收表現!$A$6:$A$3000,0))),"") | F77: =IFERROR(IF(INDEX(營收表現!E$6:E$3000,MATCH($A77,營收表現!$A$6:$A$3000,0))="","",INDEX(營收表現!E$6:E$3000,MATCH($A77,營收表現!$A$6:$A$3000,0))),"") | G77: =IFERROR(IF(INDEX(營收表現!F$6:F$3000,MATCH($A77,營收表現!$A$6:$A$3000,0))="","",INDEX(營收表現!F$6:F$3000,MATCH($A77,營收表現!$A$6:$A$3000,0))),"") | H77: =IFERROR(IF(INDEX(營收表現!G$6:G$3000,MATCH($A77,營收表現!$A$6:$A$3000,0))="","",INDEX(營收表現!G$6:G$3000,MATCH($A77,營收表現!$A$6:$A$3000,0))),"") | I77: =IFERROR(IF(INDEX(營收表現!H$6:H$3000,MATCH($A77,營收表現!$A$6:$A$3000,0))="","",INDEX(營收表現!H$6:H$3000,MATCH($A77,營收表現!$A$6:$A$3000,0))),"") | J77: =IFERROR(IF(INDEX(營收表現!I$6:I$3000,MATCH($A77,營收表現!$A$6:$A$3000,0))="","",INDEX(營收表現!I$6:I$3000,MATCH($A77,營收表現!$A$6:$A$3000,0))),"") | K77: =IFERROR(IF(INDEX(營收表現!J$6:J$3000,MATCH($A77,營收表現!$A$6:$A$3000,0))="","",INDEX(營收表現!J$6:J$3000,MATCH($A77,營收表現!$A$6:$A$3000,0))),"") | ... O77: =IFERROR(IF(INDEX(營收表現!N$6:N$3000,MATCH($A77,營收表現!$A$6:$A$3000,0))="","",INDEX(營收表現!N$6:N$3000,MATCH($A77,營收表現!$A$6:$A$3000,0))),"")
B78: =IFERROR(INDEX(營收表現!B$6:B$3000,MATCH($A78,營收表現!$A$6:$A$3000,0)),"") | C78: =IFERROR(INDEX(類別!G$4:G$3000,MATCH($A78,類別!$C$4:$C$3000,0)),"") | D78: =IFERROR(IF(INDEX(營收表現!C$6:C$3000,MATCH($A78,營收表現!$A$6:$A$3000,0))="","",INDEX(營收表現!C$6:C$3000,MATCH($A78,營收表現!$A$6:$A$3000,0))),"") | E78: =IFERROR(IF(INDEX(營收表現!D$6:D$3000,MATCH($A78,營收表現!$A$6:$A$3000,0))="","",INDEX(營收表現!D$6:D$3000,MATCH($A78,營收表現!$A$6:$A$3000,0))),"") | F78: =IFERROR(IF(INDEX(營收表現!E$6:E$3000,MATCH($A78,營收表現!$A$6:$A$3000,0))="","",INDEX(營收表現!E$6:E$3000,MATCH($A78,營收表現!$A$6:$A$3000,0))),"") | G78: =IFERROR(IF(INDEX(營收表現!F$6:F$3000,MATCH($A78,營收表現!$A$6:$A$3000,0))="","",INDEX(營收表現!F$6:F$3000,MATCH($A78,營收表現!$A$6:$A$3000,0))),"") | H78: =IFERROR(IF(INDEX(營收表現!G$6:G$3000,MATCH($A78,營收表現!$A$6:$A$3000,0))="","",INDEX(營收表現!G$6:G$3000,MATCH($A78,營收表現!$A$6:$A$3000,0))),"") | I78: =IFERROR(IF(INDEX(營收表現!H$6:H$3000,MATCH($A78,營收表現!$A$6:$A$3000,0))="","",INDEX(營收表現!H$6:H$3000,MATCH($A78,營收表現!$A$6:$A$3000,0))),"") | J78: =IFERROR(IF(INDEX(營收表現!I$6:I$3000,MATCH($A78,營收表現!$A$6:$A$3000,0))="","",INDEX(營收表現!I$6:I$3000,MATCH($A78,營收表現!$A$6:$A$3000,0))),"") | K78: =IFERROR(IF(INDEX(營收表現!J$6:J$3000,MATCH($A78,營收表現!$A$6:$A$3000,0))="","",INDEX(營收表現!J$6:J$3000,MATCH($A78,營收表現!$A$6:$A$3000,0))),"") | ... O78: =IFERROR(IF(INDEX(營收表現!N$6:N$3000,MATCH($A78,營收表現!$A$6:$A$3000,0))="","",INDEX(營收表現!N$6:N$3000,MATCH($A78,營收表現!$A$6:$A$3000,0))),"")
B79: =IFERROR(INDEX(營收表現!B$6:B$3000,MATCH($A79,營收表現!$A$6:$A$3000,0)),"") | C79: =IFERROR(INDEX(類別!G$4:G$3000,MATCH($A79,類別!$C$4:$C$3000,0)),"") | D79: =IFERROR(IF(INDEX(營收表現!C$6:C$3000,MATCH($A79,營收表現!$A$6:$A$3000,0))="","",INDEX(營收表現!C$6:C$3000,MATCH($A79,營收表現!$A$6:$A$3000,0))),"") | E79: =IFERROR(IF(INDEX(營收表現!D$6:D$3000,MATCH($A79,營收表現!$A$6:$A$3000,0))="","",INDEX(營收表現!D$6:D$3000,MATCH($A79,營收表現!$A$6:$A$3000,0))),"") | F79: =IFERROR(IF(INDEX(營收表現!E$6:E$3000,MATCH($A79,營收表現!$A$6:$A$3000,0))="","",INDEX(營收表現!E$6:E$3000,MATCH($A79,營收表現!$A$6:$A$3000,0))),"") | G79: =IFERROR(IF(INDEX(營收表現!F$6:F$3000,MATCH($A79,營收表現!$A$6:$A$3000,0))="","",INDEX(營收表現!F$6:F$3000,MATCH($A79,營收表現!$A$6:$A$3000,0))),"") | H79: =IFERROR(IF(INDEX(營收表現!G$6:G$3000,MATCH($A79,營收表現!$A$6:$A$3000,0))="","",INDEX(營收表現!G$6:G$3000,MATCH($A79,營收表現!$A$6:$A$3000,0))),"") | I79: =IFERROR(IF(INDEX(營收表現!H$6:H$3000,MATCH($A79,營收表現!$A$6:$A$3000,0))="","",INDEX(營收表現!H$6:H$3000,MATCH($A79,營收表現!$A$6:$A$3000,0))),"") | J79: =IFERROR(IF(INDEX(營收表現!I$6:I$3000,MATCH($A79,營收表現!$A$6:$A$3000,0))="","",INDEX(營收表現!I$6:I$3000,MATCH($A79,營收表現!$A$6:$A$3000,0))),"") | K79: =IFERROR(IF(INDEX(營收表現!J$6:J$3000,MATCH($A79,營收表現!$A$6:$A$3000,0))="","",INDEX(營收表現!J$6:J$3000,MATCH($A79,營收表現!$A$6:$A$3000,0))),"") | ... O79: =IFERROR(IF(INDEX(營收表現!N$6:N$3000,MATCH($A79,營收表現!$A$6:$A$3000,0))="","",INDEX(營收表現!N$6:N$3000,MATCH($A79,營收表現!$A$6:$A$3000,0))),"")
B80: =IFERROR(INDEX(營收表現!B$6:B$3000,MATCH($A80,營收表現!$A$6:$A$3000,0)),"") | C80: =IFERROR(INDEX(類別!G$4:G$3000,MATCH($A80,類別!$C$4:$C$3000,0)),"") | D80: =IFERROR(IF(INDEX(營收表現!C$6:C$3000,MATCH($A80,營收表現!$A$6:$A$3000,0))="","",INDEX(營收表現!C$6:C$3000,MATCH($A80,營收表現!$A$6:$A$3000,0))),"") | E80: =IFERROR(IF(INDEX(營收表現!D$6:D$3000,MATCH($A80,營收表現!$A$6:$A$3000,0))="","",INDEX(營收表現!D$6:D$3000,MATCH($A80,營收表現!$A$6:$A$3000,0))),"") | F80: =IFERROR(IF(INDEX(營收表現!E$6:E$3000,MATCH($A80,營收表現!$A$6:$A$3000,0))="","",INDEX(營收表現!E$6:E$3000,MATCH($A80,營收表現!$A$6:$A$3000,0))),"") | G80: =IFERROR(IF(INDEX(營收表現!F$6:F$3000,MATCH($A80,營收表現!$A$6:$A$3000,0))="","",INDEX(營收表現!F$6:F$3000,MATCH($A80,營收表現!$A$6:$A$3000,0))),"") | H80: =IFERROR(IF(INDEX(營收表現!G$6:G$3000,MATCH($A80,營收表現!$A$6:$A$3000,0))="","",INDEX(營收表現!G$6:G$3000,MATCH($A80,營收表現!$A$6:$A$3000,0))),"") | I80: =IFERROR(IF(INDEX(營收表現!H$6:H$3000,MATCH($A80,營收表現!$A$6:$A$3000,0))="","",INDEX(營收表現!H$6:H$3000,MATCH($A80,營收表現!$A$6:$A$3000,0))),"") | J80: =IFERROR(IF(INDEX(營收表現!I$6:I$3000,MATCH($A80,營收表現!$A$6:$A$3000,0))="","",INDEX(營收表現!I$6:I$3000,MATCH($A80,營收表現!$A$6:$A$3000,0))),"") | K80: =IFERROR(IF(INDEX(營收表現!J$6:J$3000,MATCH($A80,營收表現!$A$6:$A$3000,0))="","",INDEX(營收表現!J$6:J$3000,MATCH($A80,營收表現!$A$6:$A$3000,0))),"") | ... O80: =IFERROR(IF(INDEX(營收表現!N$6:N$3000,MATCH($A80,營收表現!$A$6:$A$3000,0))="","",INDEX(營收表現!N$6:N$3000,MATCH($A80,營收表現!$A$6:$A$3000,0))),"")
... B158: =IFERROR(INDEX(營收表現!B$6:B$3000,MATCH($A158,營收表現!$A$6:$A$3000,0)),"") | C158: =IFERROR(INDEX(類別!G$4:G$3000,MATCH($A158,類別!$C$4:$C$3000,0)),"") | D158: =IFERROR(IF(INDEX(營收表現!C$6:C$3000,MATCH($A158,營收表現!$A$6:$A$3000,0))="","",INDEX(營收表現!C$6:C$3000,MATCH($A158,營收表現!$A$6:$A$3000,0))),"") | E158: =IFERROR(IF(INDEX(營收表現!D$6:D$3000,MATCH($A158,營收表現!$A$6:$A$3000,0))="","",INDEX(營收表現!D$6:D$3000,MATCH($A158,營收表現!$A$6:$A$3000,0))),"") | F158: =IFERROR(IF(INDEX(營收表現!E$6:E$3000,MATCH($A158,營收表現!$A$6:$A$3000,0))="","",INDEX(營收表現!E$6:E$3000,MATCH($A158,營收表現!$A$6:$A$3000,0))),"") | G158: =IFERROR(IF(INDEX(營收表現!F$6:F$3000,MATCH($A158,營收表現!$A$6:$A$3000,0))="","",INDEX(營收表現!F$6:F$3000,MATCH($A158,營收表現!$A$6:$A$3000,0))),"") | H158: =IFERROR(IF(INDEX(營收表現!G$6:G$3000,MATCH($A158,營收表現!$A$6:$A$3000,0))="","",INDEX(營收表現!G$6:G$3000,MATCH($A158,營收表現!$A$6:$A$3000,0))),"") | I158: =IFERROR(IF(INDEX(營收表現!H$6:H$3000,MATCH($A158,營收表現!$A$6:$A$3000,0))="","",INDEX(營收表現!H$6:H$3000,MATCH($A158,營收表現!$A$6:$A$3000,0))),"") | J158: =IFERROR(IF(INDEX(營收表現!I$6:I$3000,MATCH($A158,營收表現!$A$6:$A$3000,0))="","",INDEX(營收表現!I$6:I$3000,MATCH($A158,營收表現!$A$6:$A$3000,0))),"") | K158: =IFERROR(IF(INDEX(營收表現!J$6:J$3000,MATCH($A158,營收表現!$A$6:$A$3000,0))="","",INDEX(營收表現!J$6:J$3000,MATCH($A158,營收表現!$A$6:$A$3000,0))),"") | ... O158: =IFERROR(IF(INDEX(營收表現!N$6:N$3000,MATCH($A158,營收表現!$A$6:$A$3000,0))="","",INDEX(營收表現!N$6:N$3000,MATCH($A158,營收表現!$A$6:$A$3000,0))),"")

Sheet Links
A1: 上游代號 | B1: 下游代號 | C1: 關係類型 | D1: 備註
A2: 2338 | B2: 2330 | C2: 光罩/光罩版 | D2: 示例
A3: 2449 | B3: 2330 | C3: IC封測 | D3: 示例
A4: 3680 | B4: 2330 | C4: 夾具/傳送盒 | D4: 示例
A5: 2330 | B5: 2454 | C5: 通訊晶片代工 | D5: 示例
A6: 2308 | B6: 2454 | C6: 電源/電源模組 | D6: 示例
A7: 3711 | B7: 2330 | C7: IC封測
A8: 1711 | B8: 2330 | C8: 半導體化學品
A9: 1727 | B9: 2330 | C9: 半導體化學品
A10: 1717 | B10: 2330 | C10: 半導體化學品
A11: 6239 | B11: 2330 | C11: IC封測
A12: 9933 | B12: 2330 | C12: 工程顧問
A13: 8234 | B13: 2330 | C13: 工業電腦
A14: 1560 | B14: 2330 | C14: 半導體材料
A15: 5434 | B15: 2330 | C15: 半導體材料
A16: 6532 | B16: 2330 | C16: 半導體材料通路商
A17: 3167 | B17: 2330 | C17: 半導體設備
A18: 3580 | B18: 2330 | C18: 半導體設備
A19: 3131 | B19: 2330 | C19: 半導體設備
A20: 5443 | B20: 2330 | C20: 半導體設備
A21: 2467 | B21: 2330 | C21: 半導體設備
A22: 3583 | B22: 2330 | C22: 半導體設備
... A65: 4306 | B65: 2330 | C65: 檢測驗證

Sheet ChainNodes
A1: 節點ID | B1: 名稱 | C1: 順序
A2: 1 | B2: IC設計軟體 | C2: 1
A3: 2 | B3: IC設計 | C3: 2
A4: 3 | B4: 設計IP | C4: 3
A5: 4 | B5: 矽晶圓 | C5: 4
A6: 5 | B6: 光罩 | C6: 5
A7: 6 | B7: 晶圓代工 | C7: 6
A8: 7 | B8: IC封裝 | C8: 7
A9: 8 | B9: 導線架 | C9: 8
A10: 9 | B10: BGA基板 | C10: 9
A11: 10 | B11: IC測試 | C11: 10
A12: 11 | B12: IC基板 | C12: 9
A13: 12 | B13: DRAM | C13: 11
A14: 13 | B14: 類比IC | C14: 12

Sheet ChainLinks
A1: source | B1: target
A2: 1 | B2: 2
A3: 2 | B3: 3
A4: 3 | B4: 6
A5: 4 | B5: 6
A6: 5 | B6: 6
A7: 6 | B7: 7
A8: 7 | B8: 8
A9: 7 | B9: 9
A10: 9 | B10: 10

Sheet ChainStocks
A1: 節點ID | B1: 個股 | C1: 名稱
A2: 6 | B2: 2330 | C2: 台積電
A3: 6 | B3: 2303 | C3: 聯電
A4: 6 | B4: 5347 | C4: 世界先進
A5: 7 | B5: 3711 | C5: 日月光投控
A6: 7 | B6: 2325 | C6: 矽品
A7: 5 | B7: 2338 | C7: 光罩

Sheet README
A1: 使用說明
A2: 1. Revenue：每家公司一列；月份欄位命名必須為 YYYYMM單月合併營收年成長(%) / YYYYMM單月合併營收月變動(%)。
A3: 2. Links：方向為 上游代號 ➜ 下游代號；關係類型與權重可自由維護。
A4: 3. 將本檔命名為 data.xlsx，與 index.html 放在同一層，部署到 GitHub Pages 即可。

Sheet 營收表現
A1: 格式：一般排行///文字///日期//否//否 | B1: 表格欄位/代號種類^=^S^;^週期編號^=^D^;^AllCMenuIDs^=^M009,M009^;^是否轉置^=^False^;^檢視方式^=^2^;^AllFields^=^單月合併營收月變動(%),單月合併營收年成長(%)^;^MainTable^=^^;^ListType^=^^;^SelectDate^=^TOP 6|TOP 6^;^SelectCMenuID^=^M009^;^SelectDate種類^=^1|1^;^AllFieldsNO^=^,^;^自訂欄位公式^=^|^;^自訂欄位Where條件^=^|^;^多期數值處理方式^=^1|1^;^多欄指定個股方式^=^^;^多欄指定個股^=^^;^多欄指定群組名稱^=^^;^欄位顯示狀態^=^1|1^;^欄位轉換日期方式^=^月|月^;^欄位排序方式^=^|^;^欄位採用各期最新^=^|^;^樣本表系統定義全部代號^=^^;^單項目比較欄位^=^^;^單項目比較欄位編號^=^^;^表格類型^=^ | C1: 月營收(成長與達成率).單月合併營收月變動(%)/每一期/最近/6/遞增/月// | D1: 月營收(成長與達成率).單月合併營收月變動(%) | E1: 月營收(成長與達成率).單月合併營收月變動(%) | F1: 月營收(成長與達成率).單月合併營收月變動(%) | G1: 月營收(成長與達成率).單月合併營收月變動(%) | H1: 月營收(成長與達成率).單月合併營收月變動(%) | I1: 月營收(成長與達成率).單月合併營收年成長(%)/每一期/最近/6/遞增/月// | J1: 月營收(成長與達成率).單月合併營收年成長(%) | K1: 月營收(成長與達成率).單月合併營收年成長(%) | L1: 月營收(成長與達成率).單月合併營收年成長(%) | M1: 月營收(成長與達成率).單月合併營收年成長(%) | N1: 月營收(成長與達成率).單月合併營收年成長(%)
A2: 基準日:最近一日 | B2: 資料日期/
A3: 更新標題:否 | B3: 參考標題 | C3: 202508單月合併營收月變動(%) | D3: 202509單月合併營收月變動(%) | E3: 202510單月合併營收月變動(%) | F3: 202511單月合併營收月變動(%) | G3: 202512單月合併營收月變動(%) | H3: 202601單月合併營收月變動(%) | I3: 202508單月合併營收年成長(%) | J3: 202509單月合併營收年成長(%) | K3: 202510單月合併營收年成長(%) | L3: 202511單月合併營收年成長(%) | M3: 202512單月合併營收年成長(%) | N3: 202601單月合併營收年成長(%)
A5: 股票代號 | B5: 股票名稱
A6: 1101 | B6: 台泥 | C6: -9.76 | D6: 8.94 | E6: 4.33 | F6: -5.48 | G6: 8.37 | H6: -13.83 | I6: -6.07 | J6: -0.14 | K6: -14.69 | L6: -20.49 | M6: -14.04 | N6: 0.32
A7: 1102 | B7: 亞泥 | C7: -2.96 | D7: 12.79 | E7: -8.69 | F7: 0.89 | G7: 4.88 | H7: -3.01 | I7: -15.89 | J7: -1.67 | K7: -11.25 | L7: -18.19 | M7: -12.88 | N7: 1.86
A8: 1103 | B8: 嘉泥 | C8: -5.95 | D8: -0.83 | E8: 5.02 | F8: 0.97 | G8: 10.34 | I8: -11.41 | J8: -6.02 | K8: 8.01 | L8: -3.89 | M8: -3.28
A9: 1104 | B9: 環泥 | C9: 4.86 | D9: 17.3 | E9: 2.21 | F9: -11.93 | G9: 22.35 | I9: -7.58 | J9: 18.05 | K9: 12.64 | L9: -6.76 | M9: 3.15
A10: 1108 | B10: 幸福 | C10: -3.71 | D10: 1.86 | E10: -7 | F10: 0.1 | G10: 14.31 | H10: 0.43 | I10: -9.97 | J10: -16.07 | K10: -18.03 | L10: -20.55 | M10: -25.92 | N10: -16.41
A11: 1109 | B11: 信大 | C11: -0.72 | D11: 3.93 | E11: -14.15 | F11: 8.84 | G11: 17.15 | H11: -10.07 | I11: 1.69 | J11: 19.49 | K11: -6.48 | L11: -6.21 | M11: 4.63 | N11: 22.73
A12: 1110 | B12: 東泥 | C12: 23.96 | D12: -4.12 | E12: 16.14 | F12: -20.16 | G12: 12.46 | H12: -15.88 | I12: -27.81 | J12: -21.69 | K12: 5.25 | L12: -27.68 | M12: -9.32 | N12: -16.09
A13: 1201 | B13: 味全 | C13: 6.72 | D13: 9.41 | E13: -16.61 | F13: -8.34 | G13: 1.17 | H13: 0.32 | I13: -10.93 | J13: 1.21 | K13: -11.93 | L13: -9.82 | M13: -9.69 | N13: -12.38
A14: 1203 | B14: 味王 | C14: 7.16 | D14: -4.56 | E14: -0.09 | F14: -3.22 | G14: 0.2 | H14: 6.16 | I14: -5.28 | J14: -4.02 | K14: -16.54 | L14: -24.31 | M14: -27.8 | N14: -14.52
A15: 1210 | B15: 大成 | C15: 7.84 | D15: 2.05 | E15: -3.41 | F15: 5.03 | G15: 8.29 | H15: 1.41 | I15: -5.22 | J15: 1.35 | K15: -1.98 | L15: -1.23 | M15: 4.65 | N15: 12
A16: 1213 | B16: 大飲 | C16: 46.76 | D16: -0.14 | E16: -24.18 | F16: -8.19 | G16: -11.82 | H16: 18.15 | I16: 31.97 | J16: 85.2 | K16: 37.93 | L16: 43.82 | M16: 24.48 | N16: 10.6
A17: 1215 | B17: 卜蜂 | C17: -1.63 | D17: 2.4 | E17: -1.75 | F17: 5.75 | G17: 10.78 | H17: -4.18 | I17: -3.49 | J17: 5.08 | K17: -4.49 | L17: 1.93 | M17: 13.02 | N17: 13.03
A18: 1216 | B18: 統一 | C18: 6.45 | D18: -3.92 | E18: -7.17 | F18: -5.65 | G18: 2.25 | H18: 26.37 | I18: -1.34 | J18: 0.97 | K18: -0.77 | L18: -1.12 | M18: 1.69 | N18: 0.53
A19: 1217 | B19: 愛之味 | C19: 21.57 | D19: -11.21 | E19: -30.62 | F19: -11.12 | G19: -2.82 | H19: 46.69 | I19: -14.86 | J19: 7.86 | K19: 1.24 | L19: -10.5 | M19: -5.28 | N19: -1.52
A20: 1218 | B20: 泰山 | C20: 14.28 | D20: -13.3 | E20: -10.62 | F20: -4.5 | G20: 10.17 | H20: 13.3 | I20: -0.39 | J20: -10.13 | K20: -5.02 | L20: -10.13 | M20: 14.31 | N20: 6.3
A21: 1219 | B21: 福壽 | C21: 4.08 | D21: 5.31 | E21: 4.57 | F21: -5.05 | G21: 10.79 | H21: -4.55 | I21: -1.1 | J21: 3.36 | K21: 2.73 | L21: -5.36 | M21: 5.09 | N21: 7.89
... A24: 1227 | B24: 佳格 | C24: 22.92 | D24: 25.79 | E24: -27.75 | F24: 21.2 | G24: 6.24 | H24: 36.85 | I24: -8.81 | J24: 3 | K24: 3.58 | L24: -5.4 | M24: -17.09 | N24: 16.14
A25: 1229 | B25: 聯華 | C25: 3.93 | D25: 21.43 | E25: -17.81 | F25: 25.4 | G25: 7.42 | I25: 10.78 | J25: 34.75 | K25: 21.91 | L25: 14.69 | M25: 11.25
A26: 1231 | B26: 聯華食 | C26: 2.08 | D26: -8.55 | E26: -0.94 | F26: -3.71 | G26: 27.88 | H26: -2.46 | I26: 1.74 | J26: 16.02 | K26: 0.95 | L26: 0.24 | M26: -6.7 | N26: -1.42
A27: 1232 | B27: 大統益 | C27: 1.23 | D27: 0.91 | E27: 3.59 | F27: -2.08 | G27: 9.4 | H27: 11.02 | I27: -1.65 | J27: 3.1 | K27: 0.13 | L27: -3.15 | M27: 2.22 | N27: 21.05
A28: 1233 | B28: 天仁 | C28: 11.25 | D28: 4.78 | E28: -3.23 | F28: -2.75 | G28: 15.24 | H28: -2.34 | I28: -3.74 | J28: 1.81 | K28: 12.21 | L28: -8.96 | M28: -4.25 | N28: -10.05
A29: 1234 | B29: 黑松 | C29: 4.93 | D29: -1.17 | E29: 0.05 | F29: -22.06 | G29: -6.39 | H29: 24.02 | I29: -20.66 | J29: -7.04 | K29: 17.06 | L29: -16.45 | M29: -9.57 | N29: -5.71
A30: 1235 | B30: 興泰 | C30: 46.42 | D30: 3.69 | E30: 2.58 | F30: 22.97 | G30: -54.11 | H30: 110.02 | I30: 41.92 | J30: 46.35 | K30: 40.5 | L30: 88.03 | M30: -1.99 | N30: 177.24
A31: 1236 | B31: 宏亞 | C31: 20.12 | D31: 40.7 | E31: -49.44 | F31: 3.98 | G31: 62.83 | H31: 54.25 | I31: 2.88 | J31: 26.05 | K31: -12.91 | L31: -23.51 | M31: -25.79 | N31: 2.91
A32: 1240 | B32: 茂生農經 | C32: 7.66 | D32: 8.56 | E32: -6.09 | F32: -5.29 | G32: 8.26 | H32: -10.33 | I32: -4.05 | J32: 14.81 | K32: -3.34 | L32: -6.19 | M32: -7.43 | N32: -6.64
A33: 1256 | B33: 鮮活果汁-KY | C33: 1.81 | D33: -18.79 | E33: -44.68 | F33: 3.55 | G33: 70.02 | H33: 9.63 | I33: 23.33 | J33: -2.95 | K33: 12.73 | L33: 24.45 | M33: 74.52 | N33: 36.27
A34: 1259 | B34: 安心 | C34: 1.5 | D34: -2.63 | E34: 2.61 | F34: -2.84 | G34: 0.87 | H34: 0.56 | I34: -3.17 | J34: 0.51 | K34: 4.44 | L34: 1.73 | M34: 3.67 | N34: -4.14
A35: 1264 | B35: 德麥 | C35: -3.57 | D35: 19.04 | E35: -18.24 | F35: 7.58 | G35: 24.55 | H35: 5.08 | I35: -13.27 | J35: 4.91 | K35: -1.38 | L35: -7.88 | M35: -8.59 | N35: 5.78
A36: 1268 | B36: 漢來美食 | C36: 7.57 | D36: 3.59 | E36: 0.61 | F36: 4.83 | G36: 2.56 | H36: 17.38 | I36: 5.02 | J36: -1.46 | K36: 16.57 | L36: 10.77 | M36: -3.41 | N36: -16.81
A37: 1294 | B37: 漢田生技 | C37: 19.67 | D37: 2.34 | E37: -14.3 | F37: 16.72 | G37: 19.38 | H37: 8.11 | I37: -3.92 | J37: 39.8 | K37: 43.72 | L37: 30.35 | M37: 45.41 | N37: 117.94
... A42: 1305 | B42: 華夏 | C42: 2.13 | D42: -3.21 | E42: -25.01 | F42: 11.34 | G42: 5.62 | H42: 22.87 | I42: 19.43 | J42: -19.24 | K42: -32.56 | L42: -35.93 | M42: -12.12 | N42: 3.98
A43: 1307 | B43: 三芳 | C43: -1.04 | D43: -1.59 | E43: -2.27 | F43: -6.97 | G43: -6.01 | I43: -13.82 | J43: 1.32 | K43: 6.79 | L43: -5.85 | M43: -1.11
A44: 1308 | B44: 亞聚 | C44: -1.24 | D44: 17.57 | E44: -18.55 | F44: 6.27 | G44: 5.6 | H44: -9.34 | I44: -1.99 | J44: 41.17 | K44: -5.45 | L44: -12.14 | M44: -10.85 | N44: 2.43
A45: 1309 | B45: 台達化 | C45: -6.54 | D45: 7.35 | E45: -8.57 | F45: -14.16 | G45: 14.64 | H45: 8.93 | I45: -42.78 | J45: -30.99 | K45: -28.6 | L45: -45.35 | M45: -33.03 | N45: -11.65
A46: 1310 | B46: 台苯 | C46: -8.37 | D46: 0.85 | E46: -17.61 | F46: -2.63 | G46: -7.7 | H46: 31.84 | I46: -30.93 | J46: -24.81 | K46: -22.65 | L46: -39.8 | M46: -46.33 | N46: -19.58
A47: 1312 | B47: 國喬 | C47: -15.95 | D47: 67.78 | E47: 7.87 | F47: -8.26 | G47: 12.8 | H47: -1.48 | I47: -16.45 | J47: 75.95 | K47: 117.8 | L47: 58.54 | M47: 64.75 | N47: 84.42
A48: 1313 | B48: 聯成 | C48: -3.62 | D48: 5.81 | E48: -11.96 | F48: 6.56 | G48: 3.57 | H48: 4.26 | I48: -12.3 | J48: 2.73 | K48: -13.59 | L48: -21.32 | M48: -21.03 | N48: 20.89
A49: 1314 | B49: 中石化 | C49: -25.43 | D49: 28.21 | E49: -41.75 | F49: 20.22 | G49: 22.3 | H49: 17.98 | I49: -56.58 | J49: -23.94 | K49: -57.14 | L49: -37.88 | M49: -38.98 | N49: -32.7
A50: 1315 | B50: 達新 | C50: -12.41 | D50: -18.54 | E50: -9.18 | F50: 46.1 | G50: -19.38 | I50: 13.06 | J50: -7.35 | K50: -15.45 | L50: -13.71 | M50: -11.67
A51: 1316 | B51: 上曜 | C51: 3.87 | D51: 17.57 | E51: -1.97 | F51: 46.91 | G51: 4.13 | H51: 13.99 | I51: 324.53 | J51: 171.85 | K51: 151.94 | L51: 266.03 | M51: 207.91 | N51: 233.49
A52: 1319 | B52: 東陽 | C52: 9.2 | D52: 6.48 | E52: 13.78 | F52: 1 | G52: -5.6 | H52: 2.74 | I52: -14.8 | J52: -11.12 | K52: -2.87 | L52: -8.06 | M52: -6.88 | N52: -3.56
A53: 1321 | B53: 大洋 | C53: -12.44 | D53: -3.55 | E53: 8.96 | F53: -5.25 | G53: 11.15 | H53: 16.15 | I53: -24.29 | J53: -28.07 | K53: -37.35 | L53: -37.82 | M53: -23.91 | N53: 1.19
A54: 1323 | B54: 永裕 | C54: 8.58 | D54: 12.33 | E54: -11.88 | F54: 6.62 | G54: -3.28 | H54: 10.07 | I54: -17.7 | J54: -5.43 | K54: -16.7 | L54: 6.51 | M54: -7.56 | N54: -5.22
A55: 1324 | B55: 地球 | C55: 18.3 | D55: -4.18 | E55: 4.7 | F55: -15.83 | G55: 25.04 | H55: -9.28 | I55: 1.86 | J55: 1.55 | K55: -10.28 | L55: -21.52 | M55: -6.41 | N55: 9.32
A56: 1325 | B56: 恆大 | C56: 2.16 | D56: 4.77 | E56: -3.13 | F56: 11.67 | G56: -17.67 | H56: 27.6 | I56: -12.65 | J56: -7.51 | K56: -17.3 | L56: -8.67 | M56: -13.84 | N56: -16.77
A57: 1326 | B57: 台化 | C57: -0.43 | D57: -0.58 | E57: -4 | F57: -5.71 | G57: 5.23 | H57: 13.96 | I57: -21 | J57: -16.14 | K57: -17.15 | L57: -23.38 | M57: -19.53 | N57: 4.25
A58: 1336 | B58: 台翰 | C58: 10.96 | D58: -2.81 | E58: -0.42 | F58: 5.14 | G58: -17.63 | H58: 9.08 | I58: -8.5 | J58: -0.52 | K58: -17.5 | L58: -7.22 | M58: -14.54 | N58: -1.66
A59: 1337 | B59: 再生-KY | C59: -21.21 | D59: 46.34 | E59: -10.1 | F59: -13.36 | G59: 31.5 | H59: -11.22 | I59: -28.78 | J59: 9.72 | K59: -2.51 | L59: -27.81 | M59: -23.47 | N59: -28.11
A60: 1338 | B60: 廣華-KY | C60: 2.66 | D60: 7.9 | E60: -12.81 | F60: 9.45 | G60: -8.62 | H60: -3.01 | I60: 28.26 | J60: 9.02 | K60: -2.47 | L60: 3.6 | M60: -14.62 | N60: -7.64
A61: 1339 | B61: 昭輝 | C61: -12.61 | D61: 0.1 | E61: -2.86 | F61: 2.42 | G61: 9.15 | H61: 9.14 | I61: -25.72 | J61: -23.7 | K61: -17.36 | L61: -32 | M61: -26.98 | N61: -7.7
A62: 1340 | B62: 勝悅-KY | C62: 27.81 | D62: -45.94 | E62: 30.13 | F62: -6.18 | G62: -5.88 | H62: -7.28 | I62: -79.55 | J62: -90.99 | K62: -87.57 | L62: -88.74 | M62: -88.85 | N62: -82.03
... A64: 1342 | B64: 八貫 | C64: -1.14 | D64: 23.85 | E64: -19.85 | F64: 17.43 | G64: 61.59 | H64: -15.16 | I64: -10.39 | J64: 10.16 | K64: 6.52 | L64: 4.91 | M64: 27.63 | N64: 18.22
A65: 1402 | B65: 遠東新 | C65: 2.28 | D65: 12.06 | E65: 4.27 | F65: -7.08 | G65: 10.54 | I65: -13.15 | J65: -1.73 | K65: -0.4 | L65: -5.88 | M65: -4.93
A66: 1409 | B66: 新纖 | C66: 26.12 | D66: -17.67 | E66: 4.2 | F66: -4.93 | G66: 0.97 | I66: -3.17 | J66: -17.76 | K66: -8.61 | L66: -21.17 | M66: -34.01
A67: 1410 | B67: 南染 | C67: -0.5 | D67: -29.61 | E67: 90.57 | F67: -17.82 | G67: -6.1 | H67: -0.27 | I67: -40.5 | J67: -52.73 | K67: 1.01 | L67: -28.55 | M67: -29.92 | N67: 18.55
A68: 1413 | B68: 宏洲 | C68: -15.28 | D68: -4.05 | E68: 7.62 | F68: 3.13 | G68: 0.42 | H68: -6.06 | I68: -35.43 | J68: -32.6 | K68: -17.64 | L68: -16.22 | M68: -20.69 | N68: -26.21
A69: 1414 | B69: 東和 | C69: -4.86 | D69: -9.61 | E69: 9.97 | F69: 5.56 | G69: 15.58 | H69: 0.95 | I69: -15.04 | J69: -19.65 | K69: -14.98 | L69: -8.04 | M69: -1.27 | N69: 3.16
A70: 1416 | B70: 廣豐 | C70: 20.19 | D70: -2.59 | E70: 18.79 | F70: 3.78 | G70: 4.33 | H70: -2.12 | I70: 21.72 | J70: 5.04 | K70: 32.61 | L70: 16.34 | M70: 7.22 | N70: 37.53
A71: 1417 | B71: 嘉裕 | C71: 6.96 | D71: 46.14 | E71: 65.97 | F71: -7.36 | G71: -50.48 | H71: -5.5 | I71: -42.73 | J71: 30.92 | K71: 133.33 | L71: 100.44 | M71: -39.54 | N71: 51.48
A72: 1418 | B72: 東華 | C72: -5.56 | D72: 5.88 | E72: 3333.33 | F72: 77.02 | G72: -98.45 | H72: 3505.88 | I72: -97.61 | J72: -79.78 | K72: -57.64 | L72: 105.25 | M72: -98.39 | N72: -9.72
A73: 1419 | B73: 新紡 | C73: 46.68 | D73: -7.96 | E73: -3.95 | F73: 9.85 | G73: 25.23 | H73: -12.96 | I73: 1 | J73: 12.08 | K73: 13.66 | L73: 20.83 | M73: 3.27 | N73: 51.24
A74: 1423 | B74: 利華 | C74: -16.62 | D74: 220.13 | E74: -59.62 | F74: -22.27 | G74: 72.29 | H74: -24.96 | I74: -56.83 | J74: 170.99 | K74: 18.26 | L74: -23.09 | M74: 52.22 | N74: -12.81
A75: 1432 | B75: 大魯閣 | C75: 8.25 | D75: -21.02 | E75: 1.78 | F75: -3.84 | G75: 12.93 | I75: 8.53 | J75: 2.89 | K75: 8.52 | L75: 5.22 | M75: -2.53
A76: 1434 | B76: 福懋 | C76: -0.13 | D76: -1.21 | E76: -11.59 | F76: 1.2 | G76: 17.91 | H76: 6.64 | I76: -10.54 | J76: -8.86 | K76: -15.64 | L76: -10.18 | M76: -6.08 | N76: 5.09
A77: 1435 | B77: 中福 | C77: 0.2 | D77: -0.2 | E77: 0.2 | F77: -0.2 | G77: 0.2 | H77: -0.2 | I77: -49.65 | J77: -49.7 | K77: -50.3 | L77: 0 | M77: 0.2 | N77: 0
A78: 1436 | B78: 華友聯 | C78: -69.49 | D78: -73.95 | E78: -69.37 | F78: -20.25 | G78: 369.92 | H78: -82.59 | I78: -66.45 | J78: -92.32 | K78: -93.41 | L78: -82.86 | M78: 12.74 | N78: -83.95
A79: 1437 | B79: 勤益控 | C79: -57.5 | D79: 3.02 | E79: 13.25 | F79: 3.36 | G79: -17.46 | H79: -3.81 | I79: 2.3 | J79: 7.78 | K79: 26.32 | L79: 32.08 | M79: -13.64 | N79: 19.92
A80: 1438 | B80: 三地開發 | D80: 1883.44 | E80: 2528.32 | F80: -10.14 | G80: -40.94 | H80: -33.92 | J80: -98.33
A81: 1439 | B81: 雋揚 | C81: -18.73 | D81: -93.43 | E81: -42.92 | F81: 293.42 | G81: 1410.39 | I81: 2455.19 | J81: 67 | K81: -12.94 | L81: 274.67 | M81: 2681.3
A82: 1440 | B82: 南紡 | C82: -1.91 | D82: -5.51 | E82: 8.93 | F82: -12.18 | G82: 16.69 | H82: -4.63 | I82: -33.14 | J82: -22.39 | K82: -27.24 | L82: -19.27 | M82: -5.19 | N82: -16.06
A83: 1441 | B83: 大東 | C83: 1.06 | D83: -8.85 | E83: 11.45 | F83: -1.94 | G83: 1.99 | H83: -7.13 | I83: -36.7 | J83: -6.62 | K83: -28.3 | L83: -11.35 | M83: -0.65 | N83: -12.82
A84: 1442 | B84: 名軒 | C84: -33.75 | D84: -5.59 | E84: 16.69 | F84: 12.95 | G84: 27.79 | H84: -43.71 | I84: -79.4 | J84: -79.54 | K84: -79.25 | L84: -37.33 | M84: 50.3 | N84: -57.4
A85: 1443 | B85: 立益物流 | C85: -5.6 | D85: 4.31 | E85: -6.77 | F85: -0.44 | G85: 0.85 | H85: -0.41 | I85: 1.23 | J85: -2.7 | K85: -11.84 | L85: -7.49 | M85: -7.57 | N85: -9.83
A86: 1444 | B86: 力麗 | C86: -7.87 | D86: 21.57 | E86: 5.28 | F86: -14.8 | G86: -3.86 | H86: -3.24 | I86: -25.03 | J86: -11.11 | K86: -12.58 | L86: -15.1 | M86: -25.19 | N86: -16.53
A87: 1445 | B87: 大宇 | C87: 5.27 | D87: -19.82 | E87: 52.61 | F87: -39.92 | G87: 38.83 | H87: 12.67 | I87: -33.86 | J87: -32.57 | K87: 12.08 | L87: -44.44 | M87: 19.5 | N87: -7.73
A88: 1446 | B88: 宏和 | C88: 37.2 | D88: -90.69 | E88: -18.79 | F88: 52.56 | G88: -37.65 | I88: -80.55 | J88: -97.07 | K88: -98.06 | L88: 24.32 | M88: -93.61
A89: 1447 | B89: 力鵬 | C89: 213.1 | D89: -16.69 | E89: -31.05 | F89: 69.94 | G89: -37.29 | H89: 30.65 | I89: 3.88 | J89: 36.33 | K89: -56.24 | L89: 29.28 | M89: -34.34 | N89: 4.57
A90: 1449 | B90: 佳和 | C90: -0.41 | D90: -14.08 | E90: 7.23 | F90: 84.75 | G90: 79.13 | H90: -52.68 | I90: -28.66 | J90: -36.95 | K90: -47.03 | L90: 40.04 | M90: 140.86 | N90: 10.25
A91: 1451 | B91: 年興 | C91: -14.73 | D91: 8.9 | E91: -9.37 | F91: 20.07 | G91: -5.45 | H91: 2.79 | I91: -9.03 | J91: 16.69 | K91: 10.4 | L91: -7.75 | M91: 24.74 | N91: 20.1
A92: 1452 | B92: 宏益 | C92: -12.42 | D92: 14.94 | E92: -13.25 | F92: -3.82 | G92: 0.41 | H92: -9.78 | I92: -30.05 | J92: -21.11 | K92: -27.41 | L92: -34.12 | M92: -35.68 | N92: -12.79
A93: 1453 | B93: 大將 | C93: -15.32 | D93: 0 | E93: -16.19 | F93: 107.95 | G93: -31.15 | H93: 0 | I93: -8.7 | J93: -7.89 | K93: -23.48 | L93: 60.53 | M93: 9.57 | N93: 1.61
A94: 1454 | B94: 台富 | C94: -6.65 | D94: -1.11 | E94: -2.1 | F94: -7.42 | G94: 29.29 | H94: -20.9 | I94: -20.3 | J94: -15.62 | K94: 0.93 | L94: -11.35 | M94: -13.08 | N94: -7.67
A95: 1455 | B95: 集盛 | C95: -6.01 | D95: -7.03 | E95: -6.43 | F95: -0.7 | G95: -0.33 | H95: 3.6 | I95: -43.99 | J95: -39.19 | K95: -42 | L95: -42.26 | M95: -42.89 | N95: -23.76
A96: 1456 | B96: 怡華 | C96: -69.65 | D96: -50.42 | E96: 213.79 | F96: 5.08 | G96: 81.29 | H96: -49.49 | I96: -79.38 | J96: -82.79 | K96: 8.62 | L96: 215.7 | M96: -24.95 | N96: 50.81
A97: 1457 | B97: 宜進 | C97: -11.82 | D97: 1.65 | E97: 2.45 | F97: -10.45 | G97: 5.93 | H97: 3.06 | I97: -36.75 | J97: -27.57 | K97: -12.58 | L97: -27.43 | M97: -29.9 | N97: -23.39
A98: 1459 | B98: 聯發 | C98: -0.26 | D98: 13.2 | E98: 1.82 | F98: -3.19 | G98: -25.72 | H98: 10.81 | I98: 0.09 | J98: -0.3 | K98: 1.3 | L98: -10.67 | M98: -43.86 | N98: -15.86
A99: 1460 | B99: 宏遠 | C99: 31.77 | D99: 3.04 | E99: -8.21 | F99: 8.3 | G99: 18.86 | H99: -14.15 | I99: -13.35 | J99: -12.13 | K99: -24.06 | L99: -12.4 | M99: -16.94 | N99: -3.06
A100: 1463 | B100: 強盛新 | C100: -40.73 | D100: 26.82 | E100: -4.02 | F100: -14.34 | G100: 22.53 | H100: 39.91 | I100: -45.6 | J100: -0.19 | K100: 44.51 | L100: -45.21 | M100: -94.89 | N100: -94.01
... A107: 1471 | B107: 首利 | C107: -7.07 | D107: 22.78 | E107: -18.49 | F107: -35.93 | G107: 20.7 | H107: -5.2 | I107: -43.02 | J107: -28.84 | K107: -52.72 | L107: -56.13 | M107: -55.1 | N107: -42.27
A108: 1472 | B108: 三洋實業 | C108: 7.2 | D108: -14.45 | E108: 3.69 | F108: 2.35 | G108: 6.64 | I108: 109.54 | J108: 39 | K108: 88.09 | L108: 23.81 | M108: 15.11
A109: 1473 | B109: 台南 | C109: -9.61 | D109: -41.45 | E109: -4.04 | F109: 57.18 | G109: -0.25 | H109: 48.17 | I109: -21.08 | J109: -33.76 | K109: -26.45 | L109: 1.48 | M109: -41.22 | N109: -11.65
A110: 1474 | B110: 弘裕 | C110: -4.3 | D110: 5.67 | E110: -5.36 | F110: 6.59 | G110: 4.99 | H110: -8.84 | I110: -15.57 | J110: -3 | K110: -21.13 | L110: -9.22 | M110: -12.58 | N110: 9.43
A111: 1475 | B111: 業旺 | C111: -5.85 | D111: 26.74 | E111: -21.76 | F111: 19.9 | G111: 9.78 | I111: -39.98 | J111: -23.5 | K111: -36.61 | L111: -24.89 | M111: -18.84
A112: 1476 | B112: 儒鴻 | C112: 10 | D112: -3.25 | E112: -5.19 | F112: -5.87 | G112: 14.13 | H112: 8.53 | I112: -9.67 | J112: 1.59 | K112: -6.92 | L112: 1.54 | M112: -3.57 | N112: 7.55
A113: 1477 | B113: 聚陽 | C113: 34.69 | D113: -36.93 | E113: -9.9 | F113: 21.83 | G113: 23.57 | H113: -11.74 | I113: -8.87 | J113: -28.22 | K113: -19.61 | L113: 0.48 | M113: -9.17 | N113: -19.21
A114: 1503 | B114: 士電 | C114: 10.68 | D114: 1.5 | E114: -8.69 | F114: 11.89 | G114: 37.43 | I114: 12.64 | J114: -0.76 | K114: 2.34 | L114: 2.98 | M114: 17.71
...

Sheet 類別
D1: 2 | E1: 3 | F1: 4 | G1: 5 | H1: 6 | I1: 7 | K1: 2 | N1: 11 | O1: 12 | R1: 5
C3: 代碼/ | D3: 股名 | E3: Cmoney 產業分類 | F3: 研究部 分類 次產業 | G3: 個服部 分類 次產業 | H3: 指標 股 | I3: 市值 | J3: 資料庫 更新 時間 | K3: 是否為0050 | L3: 個服部 產業分類 | M3: 繪圖特用 | N3: 詳細業務 | O3: 概念標籤 | P3: 備用1 | Q3: 備用2 | R3: 個服部 分類 次產業(加未分類)
C4: 1101 | D4: 台泥 | E4: 傳產-水泥 | F4: 水泥營建 | G4: 水泥建材 | H4: Yes | I4: 1860.3 | J4: 45526 | K4: YES | L4: 水泥建材 | M4: 水泥建材 | N4: 水泥、電廠開發(火力、太陽能、 風力、地熱)、储能、充電樁、鋰電池 | R4: 水泥建材
C5: 1102 | D5: 亞泥 | E5: 傳產-水泥 | F5: 水泥營建 | G5: 水泥建材 | H5: Yes | I5: 1471.8 | L5: 食品 | M5: 食品 | N5: 水泥、電廠開發(天然氣) | R5: 水泥建材
C6: 1103 | D6: 嘉泥 | E6: 傳產-水泥 | F6: 水泥營建 | G6: 水泥建材 | I6: 113.4 | L6: 塑膠 | M6: 塑膠 | N6: 水泥、生產、銷售 | R6: 水泥建材
C7: 1104 | D7: 環泥 | E7: 傳產-水泥 | F7: 水泥營建 | G7: 水泥建材 | I7: 187.8 | L7: 營建與營造 | M7: 營建與 營造 | N7: 水泥及預拌混凝土之製造與銷售、石膏板之生產、加工及銷售與進、出口、代理銷售、其餘請參考本公司登記營業項目、 | R7: 水泥建材
C8: 1108 | D8: 幸福 | E8: 傳產-水泥 | F8: 水泥營建 | G8: 水泥建材 | I8: 59.7 | L8: 汽機車零組件 | M8: 汽機車 零組件 | N8: 有關水泥及水泥製品之工業及相關事業 | R8: 水泥建材
C9: 1109 | D9: 信大 | E9: 傳產-水泥 | F9: 水泥營建 | G9: 水泥建材 | I9: 56.8 | L9: 製鞋與紡纖 | M9: 製鞋與 紡纖 | N9: 有關水泥及水泥製品之生產及運銷 | R9: 水泥建材
C10: 1110 | D10: 東泥 | E10: 傳產-水泥 | F10: 水泥營建 | G10: 水泥建材 | I10: 102.4 | L10: 觀光餐飲 | M10: 觀光餐飲 | N10: (1)水泥製造與買賣(2)石灰石之開採及銷售、(3)水泥加工製品及預拌混凝土之製造及銷售、(4)廠房及大樓出租業(5)廢棄物處理業 | R10: 水泥建材
C11: 1201 | D11: 味全 | E11: 傳產-食品 | F11: 消費觀光 | G11: 食品 | I11: 83 | L11: 物流倉儲 | M11: 物流倉儲 | N11: 食品製造及販賣 | R11: 食品
C12: 1203 | D12: 味王 | E12: 傳產-食品 | F12: 消費觀光 | G12: 食品 | I12: 96.7 | L12: 供電與變壓 | M12: 供電與變壓 | N12: 味精醬油罐頭調理速食品飲料等製造及營銷有關進出口業務、洋菸酒類及飲料之進口及經銷、汽車檢驗及修理 | R12: 食品
C13: 1210 | D13: 大成 | E13: 傳產-食品 | F13: 消費觀光 | G13: 食品 | H13: Yes | I13: 569.1 | L13: 電機 | M13: 電機 | N13: 飼料、大宗油脂、肉品 | R13: 食品
C14: 1213 | D14: 大飲 | E14: 傳產-食品 | F14: 消費觀光 | G14: 食品 | I14: 7.2 | L14: 運動健身器材 | M14: 運動健身 器材 | N14: 製造蘋果汽水礦泉水及各種汽水飲料等之批發、經銷各國及國內有關飲料之產品副產品加工產品、百貨批發 | R14: 食品
C15: 1215 | D15: 卜蜂 | E15: 傳產-食品 | F15: 消費觀光 | G15: 食品 | H15: Yes | I15: 377.3 | L15: 工具機與機械元件 | M15: 工具機與 機械元件 | N15: 各種飼料生產加工配製銷售進口及買賣、各種禽畜育種、電動屠宰業務及各種禽畜加工品製品銷售、各種肉類加工品與調理食品及蛋品生產銷售等業務 | R15: 食品
C16: 1216 | D16: 統一 | E16: 傳產-食品 | F16: 消費觀光 | G16: 食品 | H16: Yes | I16: 4772.9 | K16: YES | L16: 鋼鐵金屬 | M16: 鋼鐵金屬 | N16: 食品、便利商店、流通、包裝容器 | R16: 食品
C17: 1217 | D17: 愛之味 | E17: 傳產-食品 | F17: 消費觀光 | G17: 食品 | I17: 51.9 | L17: 汽機車電子 | M17: 汽機車 電子 | N17: 食品 | R17: 食品
C18: 1218 | D18: 泰山 | E18: 傳產-食品 | F18: 消費觀光 | G18: 食品 | I18: 97.8 | L18: 公共工程 | M18: 公共工程 | N18: 各種食用油脂之精製及批發零售各種清涼飲料冷凍調理食品、各種禽畜魚類飼料之加工製造及買賣 | R18: 食品
C19: 1219 | D19: 福壽 | E19: 傳產-食品 | F19: 消費觀光 | G19: 食品 | I19: 49.3 | L19: 半導體設備 | M19: 半導體 設備 | N19: 食用油脂、動物飼料、穀物食品、寵物食品、有機肥料等生產及銷售、進出口國際貿易、大宗穀物進口與銷售 | R19: 食品
C20: 1220 | D20: 台榮 | E20: 傳產-食品 | F20: 消費觀光 | G20: 食品 | I20: 24.7 | L20: 資訊機構件 | M20: 資訊機構件 | N20: 飼料製造販賣、果糖製造販賣、玉米澱粉製造販賣 | R20: 食品
C21: 1225 | D21: 福懋油 | E21: 傳產-食品 | F21: 消費觀光 | G21: 食品 | I21: 69 | L21: 新能源 | M21: 新能源 | N21: 麵粉，飼料，黃豆油，黃豆粉，大麥片，玉米粉之製造與銷售、家畜，家禽之養殖及肉類之加工銷售、一般進口貿易業務(許可業務除外)、 | R21: 食品
C22: 1227 | D22: 佳格 | E22: 傳產-食品 | F22: 消費觀光 | G22: 食品 | H22: Yes | I22: 297.9 | L22: 電線電纜 | M22: 電線電纜 | N22: 嬰兒麥粉，麥片及相關產品之生產製造、食用油及滋養飲料粉之分裝，加工，銷售業務、一般進出口貿易 | R22: 食品
C23: 1229 | D23: 聯華 | E23: 傳產-食品 | F23: 消費觀光 | G23: 食品 | H23: Yes | I23: 792.8 | L23: 傢俱家電 | M23: 傢俱家電 | N23: 麵粉 | R23: 食品
C24: 1231 | D24: 聯華食 | E24: 傳產-食品 | F24: 消費觀光 | G24: 食品 | H24: Yes | I24: 382.5 | L24: LED | M24: LED | N24: 食品 | R24: 食品
C25: 1232 | D25: 大統益 | E25: 傳產-食品 | F25: 消費觀光 | G25: 食品 | I25: 241.6 | L25: 藥品製造 | M25: 藥品製造 | N25: 黃豆油、粉加工，製造及銷售 | R25: 食品
C26: 1233 | D26: 天仁 | E26: 傳產-食品 | F26: 消費觀光 | G26: 食品 | I26: 28.3 | L26: 醫美保健通路 | M26: 醫美保健 通路 | N26: 茶葉製造加工、茶葉製品買賣、茶相關製品 | R26: 食品
C27: 1234 | D27: 黑松 | E27: 傳產-食品 | F27: 消費觀光 | G27: 食品 | I27: 161.6 | L27: 化工 | M27: 化工 | N27: 碳酸飲料，酒類，果蔬汁，咖啡飲料，運動飲料等 | R27: 食品
C28: 1235 | D28: 興泰 | E28: 傳產-食品 | F28: 消費觀光 | G28: 食品 | I28: 106.8 | L28: 醫材 | M28: 醫材 | N28: 飼料 | R28: 食品
C29: 1236 | D29: 宏亞 | E29: 傳產-食品 | F29: 消費觀光 | G29: 食品 | I29: 18.7 | L29: 新藥研發 | M29: 新藥研發 | N29: 糖果、餅乾、巧克力之製造、加工及買賣、月餅、西點、麵包糕餅等食品之製造、加工及買賣、七七巧克力、禮坊名店、 | R29: 食品
C30: 1256 | D30: 鮮活果汁-KY | E30: 傳產-食品 | F30: 消費觀光 | G30: 食品 | I30: 39.9 | L30: 橡膠 | M30: 橡膠 | N30: 果汁、果粒、果粉類等產品之生產與銷售 | R30: 食品
C31: 1301 | D31: 台塑 | E31: 傳產-塑膠 | F31: 塑化橡 | G31: 塑膠 | H31: Yes | I31: 2196.2 | K31: YES | L31: 紙業 | M31: 紙業 | N31: 聚氯乙烯(PVC)、氯乙烯、液(石咸)、聚丙烯、高密度聚乙烯、聚乙烯醋酸乙烯酯、低密度聚乙烯、線性低密度聚乙烯、丙烯酸酯、高吸水性樹脂、碳素纖維、丙烯睛、甲基丙烯酸甲酯及環氧氯丙烷等 | R31: 塑膠
C32: 1303 | D32: 南亞 | E32: 傳產-塑膠 | F32: 塑化橡 | G32: 塑膠 | H32: Yes | I32: 2165.1 | K32: YES | L32: 汽機車製造或代理 | M32: 汽機車製造 或代理 | N32: 各種塑膠加工品、塑膠原料、電子材料、聚酯纖維之製銷、及染整加工、配電盤 | R32: 塑膠
C33: 1304 | D33: 台聚 | E33: 傳產-塑膠 | F33: 塑化橡 | G33: 塑膠 | I33: 109.6 | L33: 散熱 | M33: 散熱 | N33: 塑膠原料之製造、加工及銷售、電子材料、其他 | R33: 塑膠
C34: 1305 | D34: 華夏 | E34: 傳產-塑膠 | F34: 塑化橡 | G34: 塑膠 | I34: 56.5 | L34: IC代工 | M34: IC代工 | N34: 從事生產與銷售塑膠布，塑膠皮，塑膠管，塑膠粒、塑膠粉，鹼氯品及其它有關產品為主要業務 | R34: 塑膠
C35: 1307 | D35: 三芳 | E35: 傳產-塑膠 | F35: 塑化橡 | G35: 塑膠 | I35: 128.3 | L35: 影像與監控 | M35: 影像與 監控 | N35: 聚氨基甲酸加工品之製銷事項不織布起毛布加工品製銷染整事項、聚氯乙烯加工之製銷事項塑膠加工品生產技術研究改良事項、各種皮革加工之製銷事項有關事業之投資經營事項 | R35: 塑膠
C36: 1308 | D36: 亞聚 | E36: 傳產-塑膠 | F36: 塑化橡 | G36: 塑膠 | I36: 66.2 | L36: EMS | M36: EMS | N36: 低密度聚乙烯及乙烯醋酸乙烯酯共聚合樹脂之生產及銷售、高密度聚乙烯及線型低密度聚乙烯之銷售、分解性塑膠原料之製造及銷售 | R36: 塑膠
C37: 1309 | D37: 台達化 | E37: 傳產-塑膠 | F37: 塑化橡 | G37: 塑膠 | I37: 39.7 | L37: PCB製造 | M37: PCB製造 | N37: 聚苯乙烯及加工品之製銷，丙烯(月青)、丁二烯、苯乙烯共聚體樹脂、ABS之製銷，﹝丙烯(月青)、苯乙烯共聚合樹脂﹞SAN之製銷、玻璃棉及其有關產品之製銷，塑膠原料及加工品之製銷 | R37: 塑膠
C38: 1310 | D38: 台苯 | E38: 傳產-塑膠 | F38: 塑化橡 | G38: 塑膠 | I38: 40.2 | L38: 網通 | M38: 網通 | N38: 苯乙烯單體、對二乙苯、甲苯乙苯 | R38: 塑膠
C39: 1312 | D39: 國喬 | E39: 傳產-塑膠 | F39: 塑化橡 | G39: 塑膠 | I39: 102.6 | L39: 電腦週邊 | M39: 資訊週邊 | N39: 石油化工原料製造業、合成樹脂及塑膠製造業、國際貿易業(除許可業務外得經營法令非禁止或限制之業務) | R39: 塑膠
C40: 1313 | D40: 聯成 | E40: 傳產-塑膠 | F40: 塑化橡 | G40: 塑膠 | H40: Yes | I40: 107.1 | L40: 被動元件 | M40: 被動元件 | N40: 有機酸及其衍生物、塑膠增韌劑、樹脂及塑膠原料 | R40: 塑膠
C41: 1314 | D41: 中石化 | E41: 傳產-塑膠 | F41: 塑化橡 | G41: 塑膠 | I41: 250.6 | L41: 連接元件 | M41: 連接元件 | N41: 石油化學產品CPLAN之製造及銷售 | R41: 塑膠
C42: 1315 | D42: 達新 | E42: 傳產-塑膠 | F42: 塑化橡 | G42: 塑膠 | I42: 65.6 | L42: IC封測 | M42: IC封測 | N42: 塑膠雨衣、什加工、PP瓦楞板、成衣等製品、傢俱、文具、護貝、皮件等製品、醫療器材製造、批發、零售 | R42: 塑膠
C43: 1316 | D43: 上曜 | E43: 傳產-營建 | F43: 水泥營建 | G43: 營建與營造 | I43: 49.4 | L43: NB MB | M43: NB MB | N43: 房地銷售、PU合成樹酯 | R43: 營建與營造
C44: 1319 | D44: 東陽 | E44: 傳產-汽車零組件 | F44: 汽車 | G44: 汽機車零組件 | H44: Yes | I44: 554.8 | L44: 記憶體 | M44: 記憶體 | N44: 售後維修(塑膠件、鈑金件、車燈)、OEM | R44: 汽機車零組件
C45: 1321 | D45: 大洋 | E45: 傳產-塑膠 | F45: 塑化橡 | G45: 塑膠 | I45: 80.4 | L45: 功率半導體 | M45: 功率 半導體 | N45: 塑膠原料之製造及銷售、塑膠製品之製造及銷售、塑膠工業附帶原料之製造及銷售 | R45: 塑膠
C46: 1323 | D46: 永裕 | E46: 傳產-塑膠 | F46: 塑化橡 | G46: 塑膠 | I46: 18.1 | L46: 電子通路 | M46: 電子通路 | N46: 製瓶廠製品31.61%、束帶廠製品28.01%、射出廠製品18.35%、軟管廠製品13.31%、其他8.72%(各種塑膠製品製造批發、各種塑膠模具及機械零件之加工製造及買賣、塑膠原料染色之加工業務) | R46: 塑膠
C47: 1324 | D47: 地球 | E47: 傳產-塑膠 | F47: 塑化橡 | G47: 塑膠 | I47: 8 | L47: 儀器設備 | M47: 儀器設備 | N47: 各種黏膠帶電報紙防水紙防蝕漆防蝕膠帶等之製造加工買賣業務、機械設計之製造加工按裝修護買賣及電子產品之製造加工買賣業務、禮品雜貨等之買賣業務 | R47: 塑膠
C48: 1325 | D48: 恆大 | E48: 傳產-塑膠 | F48: 塑化橡 | G48: 未分類-傳產 | I48: 24.5 | L48: 顯示觸控驅動IC | M48: 顯示觸控 驅動IC | N48: 各類不織布之產銷 | R48: 未分類-傳產
C49: 1326 | D49: 台化 | E49: 傳產-塑膠 | F49: 塑化橡 | G49: 塑膠 | H49: Yes | I49: 1330.5 | K49: YES | L49: 網通IC | M49: 網通IC | N49: 純對苯二甲酸、聚苯乙烯、苯乙烯、鄰二甲苯、對二甲苯、苯、、合成酚、丙酮、聚丙烯、二甲基甲醯胺、ABS、嫘縈棉、、合成纖維紗、布、耐隆絲、耐隆絲布及其染整加工等製銷 | R49: 塑膠
C50: 1337 | D50: 再生-KY | E50: 傳產-塑膠 | F50: 塑化橡 | G50: 塑膠 | I50: 14.3 | L50: PCB材料 | M50: PCB材料 | N50: 以廢塑膠再生運用以產製EVA之共混發泡製品之製造及銷售 | R50: 塑膠
C51: 1338 | D51: 廣華-KY | E51: 傳產-汽車零組件 | F51: 汽車 | G51: 汽機車零組件 | I51: 19.7 | L51: 工業電腦 | M51: 工業電腦 | N51: 汽車內飾件之曲面印刷、表面塗裝及射出成型等製造及銷售、汽車內飾件之模具製造及銷售、其他 | R51: 汽機車零組件
C52: 1339 | D52: 昭輝 | E52: 傳產-汽車零組件 | F52: 汽車 | G52: 汽機車零組件 | I52: 36 | L52: MCU | M52: MCU | N52: 汽車零組件之製造及銷售 | R52: 汽機車零組件
C53: 1340 | D53: 勝悅-KY | E53: 傳產-塑膠 | F53: 塑化橡 | G53: 塑膠 | I53: 9.6 | L53: 面板製造或代工 | M53: 面板製造 或代工 | N53: 從事高分子複合材料之研發與應用，目前主要應用於各式鞋底材料 | R53: 塑膠
C54: 1341 | D54: 富林-KY | E54: 傳產-塑膠 | F54: 塑化橡 | G54: 塑膠 | I54: 35.4 | L54: 電信媒體 | M54: 電信媒體 | N54: 乳膠皮、膠布、及柔軟皮等PVC皮革與環保PU皮革之生產銷售 | R54: 塑膠
C55: 1342 | D55: 八貫 | E55: 傳產-塑膠 | F55: 塑化橡 | G55: 塑膠 | I55: 65.6 | L55: 電聲元件 | M55: 電聲元件 | N55: 高端醫療、救生、航太及戶外用機能性布料及成品 | R55: 塑膠
C56: 1402 | D56: 遠東新 | E56: 傳產-紡織纖維 | F56: 紡織纖維 | G56: 製鞋與紡纖 | H56: Yes | I56: 1758.4 | L56: 軟體與韌體 | M56: 軟體與韌體 | N56: 聚酯化纖 | R56: 製鞋與紡纖
C57: 1409 | D57: 新纖 | E57: 傳產-紡織纖維 | F57: 紡織纖維 | G57: 製鞋與紡纖 | I57: 196.6 | L57: 光電材料 | M57: 光電材料 | N57: 聚酯事業部69.27%、金融證券部16.04%、光電事業部14.56%(各種合成纖維及各種合成纖維假撚絲之製造及銷售、各種工程用塑膠及其加工品之製造及銷售、各種合成薄膜、膠片及有關合成薄膜原料及加工品之製造及銷售、) | R57: 製鞋與紡纖
C58: 1410 | D58: 南染 | E58: 傳產-紡織纖維 | F58: 紡織纖維 | G58: 製鞋與紡纖 | I58: 21.9 | L58: 光通訊 | M58: 光通訊 | N58: 絲棉毛合成化學纖維織品之印染及樹脂加工定型整理業務、前各項有關產品及原材料之買賣，進出口布匹業務、工業廠房開發租售，廠房出租，倉庫出租，辦公大樓出租業 | R58: 製鞋與紡纖
C59: 1413 | D59: 宏洲 | E59: 傳產-紡織纖維 | F59: 紡織纖維 | G59: 製鞋與紡纖 | I59: 15.5 | L59: 百貨零售 | M59: 百貨零售 | N59: POY87.42%、CHIPS12.58%、加工絲%、熔噴不織布%(合成化學纖維之製造及加工買賣業務、塑膠抽絲品之製造及加工買賣業務) | R59: 製鞋與紡纖
C60: 1414 | D60: 東和 | E60: 傳產-紡織纖維 | F60: 紡織纖維 | G60: 製鞋與紡纖 | I60: 39.9 | L60: 航運 | M60: 航運 | N60: 天然纖維紡織及其加工業務、 | R60: 製鞋與紡纖
C61: 1416 | D61: 廣豐 | E61: 傳產-其他 | F61: 其他傳產 | G61: 製鞋與紡纖 | I61: 21.5 | L61: 航太 | M61: 航太 | N61: 家用紡織品進出口銷售業務、委託興建國民住宅，商業大樓出租出售業務 | R61: 製鞋與紡纖
C62: 1417 | D62: 嘉裕 | E62: 傳產-紡織纖維 | F62: 紡織纖維 | G62: 製鞋與紡纖 | I62: 15.1 | L62: 油電氣 | M62: 油電氣 | N62: 男女成衣 | R62: 製鞋與紡纖
C63: 1418 | D63: 東華 | E63: 傳產-紡織纖維 | F63: 紡織纖維 | G63: 製鞋與紡纖 | I63: 11.5 | L63: 金融租賃 | M63: 金融租賃 | N63: 聚丙烯青合成纖維聚丙烯青梳毛條之製造及內外銷、生產聚丙烯青紗內外銷、聚尿酯系纖維及其原料之製造加工及內外銷 | R63: 製鞋與紡纖
C64: 1419 | D64: 新紡 | E64: 傳產-紡織纖維 | F64: 紡織纖維 | G64: 未分類-傳產 | I64: 171 | L64: 光學鏡片 | M64: 光學鏡片 | N64: 紡織商品49.33%、品牌成衣37.33%、租賃收入13.34%(紡織品之製造、加工買賣業務、紡織品成衣加工、製造、買賣及門市零售業務、委託營造廠興建商業大樓及國民住宅出租出售業務) | R64: 未分類-傳產
C65: 1423 | D65: 利華 | E65: 傳產-紡織纖維 | F65: 紡織纖維 | G65: 製鞋與紡纖 | I65: 36.9 | L65: 高速介面 | M65: 高速介面 | N65: 毛條(包括炭化羊毛)之製造及銷售業務、其他羊毛之防縮、染整加工業務、前列各款所列有關業務之進出口業務 | R65: 製鞋與紡纖
C66: 1432 | D66: 大魯閣 | E66: 傳產-百貨 | F66: 消費觀光 | G66: 觀光餐飲 | I66: 18.3 | L66: IP | M66: IP | N66: 商場開發、休閒育樂、策略事業 | R66: 觀光餐飲
C67: 1434 | D67: 福懋 | E67: 傳產-紡織纖維 | F67: 紡織纖維 | G67: 製鞋與紡纖 | H67: Yes | I67: 279.7 | L67: IC載板 | M67: IC載板 | N67: 尼龍多富達布、聚酯布、傘骨槽骨、輪胎簾布、棉紗、人造棉紗、合成纖維紗、混紡紗、織布染整、成衣、被單、床單等及其相關製品、製造高分子聚合物製品、防彈衣背心、夾克、工業用工作服 | R67: 製鞋與紡纖
C68: 1435 | D68: 中福 | E68: 傳產-其他 | F68: 其他傳產 | G68: 物流倉儲 | I68: 45.4 | L68: 面板觸控零組件 | M68: 面板觸控 零組件 | N68: 倉儲業、國際貿易，服飾批發，煙酒零售、電信器材批發業，電子材料批發業 | R68: 物流倉儲
C69: 1436 | D69: 華友聯 | E69: 傳產-營建 | F69: 水泥營建 | G69: 營建與營造 | H69: Yes | I69: 158.6 | L69: 類比與管理IC | M69: 類比與 管理IC | N69: 住宅及大樓開發租售業、休閒活動場館業、餐館業 | R69: 營建與營造
C70: 1437 | D70: 勤益控 | E70: 傳產-其他 | F70: 其他傳產 | G70: 營建與營造 | I70: 67 | L70: 光感測 | M70: 光感測 | N70: 一般投資業 | R70: 營建與營造
C71: 1438 | D71: 三地開發 | E71: 傳產-營建 | F71: 水泥營建 | G71: 營建與營造 | I71: 42.9 | L71: 晶圓製造 | M71: 晶圓製造 | N71: 委託營造廠商興建商業大樓、工業大樓及住宅出租出售業務、紡織工業之產銷及其附屬事業暨投資金融與其他經濟事業、 | R71: 營建與營造
C72: 1439 | D72: 雋揚 | E72: 傳產-紡織纖維 | F72: 紡織纖維 | G72: 製鞋與紡纖 | I72: 27.7 | L72: 電池 | M72: 電池 | N72: 委託營造廠商興建商業大樓、國民住宅及廠辦等不動產之出租及出售、建築材料之買賣製造代理、工業廠房開發租售業 | R72: 製鞋與紡纖
C73: 1440 | D73: 南紡 | E73: 傳產-紡織纖維 | F73: 紡織纖維 | G73: 未分類-傳產 | I73: 217 | L73: 遊戲 | M73: 遊戲 | N73: 各種紡織品之製造加工及販賣、有關合成纖維製品之製造及販賣、委託營造廠興建國民住宅、商業大樓出租、出售業務 | R73: 未分類-傳產
C74: 1441 | D74: 大東 | E74: 傳產-紡織纖維 | F74: 紡織纖維 | G74: 製鞋與紡纖 | I74: 8.3 | N74: 棉紗，混紡紗，化纖紗、布 | R74: 製鞋與紡纖
C75: 1442 | D75: 名軒 | E75: 傳產-營建 | F75: 水泥營建 | G75: 營建與營造 | H75: Yes | I75: 261.5 | N75: 營建99.81%、其他0.19%(營建) | R75: 營建與營造
C76: 1443 | D76: 立益物流 | E76: 傳產-航運 | F76: 航運 | G76: 製鞋與紡纖 | I76: 43 | N76: 倉儲、物流、理貨加工、電子商務、棉紡、貿易、委託營造廠商興建商業大樓及國民住宅出租出售 | R76: 製鞋與紡纖
C77: 1444 | D77: 力麗 | E77: 傳產-紡織纖維 | F77: 紡織纖維 | G77: 製鞋與紡纖 | I77: 63.6 | N77: 聚酯加工絲、聚酯原絲+粒、瓶用酯粒 | R77: 製鞋與紡纖
C78: 1445 | D78: 大宇 | E78: 傳產-紡織纖維 | F78: 紡織纖維 | G78: 製鞋與紡纖 | I78: 18.3 | N78: 紡織事業部51.77%、假撚事業部47.09%、能源部1.14%(各種紡織品之製造，加工染整及營銷、有關前項有關原料，材料及成品之進出口貿易業務、委託營造廠商興建商業大樓，國民住宅之出租出售事業) | R78: 製鞋與紡纖
C79: 1446 | D79: 宏和 | E79: 傳產-紡織纖維 | F79: 紡織纖維 | G79: 製鞋與紡纖 | I79: 32.9 | N79: 紡織、成衣 | R79: 製鞋與紡纖
C80: 1447 | D80: 力鵬 | E80: 傳產-紡織纖維 | F80: 紡織纖維 | G80: 製鞋與紡纖 | I80: 53.3 | N80: 尼龍粒、平(針)織布、尼龍絲 | R80: 製鞋與紡纖
C81: 1449 | D81: 佳和 | E81: 傳產-紡織纖維 | F81: 紡織纖維 | G81: 製鞋與紡纖 | I81: 12.4 | N81: 纖維紡織品之加工及買賣、紡織品及機械之進出口及買賣、委託興建商業大樓等 | R81: 製鞋與紡纖
C82: 1451 | D82: 年興 | E82: 傳產-紡織纖維 | F82: 紡織纖維 | G82: 製鞋與紡纖 | I82: 37.2 | N82: 紡紗業、織布業、成衣業 | R82: 製鞋與紡纖
C83: 1452 | D83: 宏益 | E83: 傳產-紡織纖維 | F83: 紡織纖維 | G83: 製鞋與紡纖 | I83: 15.1 | N83: 聚酯加工絲100%(聚酯加工絲) | R83: 製鞋與紡纖
C84: 1453 | D84: 大將 | E84: 傳產-營建 | F84: 水泥營建 | G84: 製鞋與紡纖 | I84: 14.4 | N84: 租金收入100%(營建、紡織) | R84: 製鞋與紡纖
C85: 1454 | D85: 台富 | E85: 傳產-紡織纖維 | F85: 紡織纖維 | G85: 製鞋與紡纖 | I85: 19.3 | N85: 成品布46.81%、紗42.64%、胚布10.54%、其他0.01%(特多龍布、特多龍紗) | R85: 製鞋與紡纖
C86: 1455 | D86: 集盛 | E86: 傳產-紡織纖維 | F86: 紡織纖維 | G86: 製鞋與紡纖 | I86: 47 | N86: 各種纖維絲、人造棉絲、尼龍絲之紡製、、織造、染整、印花、加工、買賣、石油化學工業纖維原料生產、銷售及進出口買賣、 | R86: 製鞋與紡纖
C87: 1456 | D87: 怡華 | E87: 傳產-營建 | F87: 水泥營建 | G87: 製鞋與紡纖 | I87: 11.7 | N87: 住宅及大樓開發租售業務、工業廠房開發租售業務、纖維紡織品之加工及買賣、 | R87: 製鞋與紡纖
... C102: 1475 | D102: 業旺 | E102: 傳產-紡織纖維 | F102: 紡織纖維 | G102: 製鞋與紡纖 | I102: 25.6 | N102: 提花布織造、染整與銷售、紡織產品使用之染料及助劑銷售 | R102: 製鞋與紡纖
C103: 1476 | D103: 儒鴻 | E103: 傳產-紡織纖維 | F103: 紡織纖維 | G103: 製鞋與紡纖 | H103: Yes | I103: 1099 | N103: 彈性針織布、成衣(主要為運動) | R103: 製鞋與紡纖
C104: 1477 | D104: 聚陽 | E104: 傳產-紡織纖維 | F104: 紡織纖維 | G104: 製鞋與紡纖 | H104: Yes | I104: 611.8 | N104: 成衣、布 | R104: 製鞋與紡纖
C105: 1503 | D105: 士電 | E105: 傳產-電機 | F105: 其他傳產 | G105: 電機 | H105: Yes | I105: 937.8 | N105: 電力配電、車輛零件、自動化設備及零件 | R105: 電機
C106: 1504 | D106: 東元 | E106: 傳產-電機 | F106: 其他傳產 | G106: 電機 | H106: Yes | I106: 995.6 | N106: 機電系統、智慧能源事業、智慧生活事業 | R106: 電機
C107: 1506 | D107: 正道 | E107: 傳產-汽車零組件 | F107: 汽車 | G107: 汽機車零組件 | I107: 34.7 | N107: 車輛零組件83.34%、系統櫃16.66%(引擎、機車、汽車等及其零件之製造買賣、活塞、活塞肖、活塞環及其配件之製造及買賣、轉向系統零件之製造及買賣) | R107: 汽機車零組件
C108: 1512 | D108: 瑞利 | E108: 傳產-汽車零組件 | F108: 汽車 | G108: 汽機車零組件 | I108: 8.6 | N108: 一、電氣、機械、五金、工具及農機、車輛配件製造銷售、二、機車、裝配組立及其內外銷、三、家具及其配件之製造銷售、四、模具、治、具及飛機零配件之製造銷售、五、軌道車輛零配件之製造銷售、 | R108: 汽機車零組件
C109: 1513 | D109: 中興電 | E109: 傳產-電機 | F109: 其他傳產 | G109: 電機 | H109: Yes | I109: 817.5 | N109: 電機電力(GIS)、停車場設備、供電系統及電力監控工程 | R109: 電機
C110: 1514 | D110: 亞力 | E110: 傳產-電機 | F110: 其他傳產 | G110: 電機 | H110: Yes | I110: 275.8 | N110: 配電盤、電機器材、電子產品、變壓器 | R110: 電機
C111: 1515 | D111: 力山 | E111: 傳產-電機 | F111: 其他傳產 | G111: 運動健身器材 | I111: 50.1 | N111: 工具機及其零件之製造加工買賣、健身機及其零件之製造加工買賣 | R111: 運動健身器材
C112: 1516 | D112: 川飛 | E112: 傳產-其他 | F112: 其他傳產 | G112: 電機 | I112: 6.1 | N112: 國際貿易 | R112: 電機
C113: 1517 | D113: 利奇 | E113: 傳產-電機 | F113: 其他傳產 | G113: 運動健身器材 | I113: 22.4 | N113: 汽、機車、腳踏車零件之製造、加工及買賣、一般機械製造、加工及買賣 | R113: 運動健身器材
C114: 1519 | D114: 華城 | E114: 傳產-電機 | F114: 其他傳產 | G114: 電機 | H114: Yes | I114: 1657.1 | N114: 變壓器、配電盤 | R114: 電機
C115: 1521 | D115: 大億 | E115: 傳產-汽車零組件 | F115: 汽車 | G115: 汽機車零組件 | I115: 19.5 | N115: 經營汽、機車、五金等零件之製造、銷售及進出口貿易業務、航空飛機零件及航海船舶之製造加工銷售業務、交通用機械及其零件之製造加工銷售業務等、 | R115: 汽機車零組件
...
